Workbook
Name DataEntryRange: Income!$A$1:$P$23
Name IncomeK4: Income!$K$4
Name Remaining_Balance: 'Person 2 Draw-down'!$AL$7
Name Remaining_Balance: 'Person 1 Draw-down'!$AL$7

Sheet Welcome
B1: Welcome!
B4: How do I use this spreadsheet? Follow these simple steps: 1) Go to the 'Income' sheet and enter your details. If you have one, enter your partner's details. 2) Go to 'Person 1 Draw-down' sheet and enter your Year of Birth, when you would like to start your retirement and when you think it'll end. Also, enter an amount that you would like to be left at the end of your retirement, the default being £0. 3) Click the 'Calculate Pension' button and wait for the calculation to complete. Detailed draw-down amounts are now visible in the 'Person 1 Draw-down' sheet. You can view the information monthly or annually by clicking the button. This is now your first insight into what your retirement might look like. If relevant, do the same for your partner and then also view your combined picture in the 'Combined Pensions' sheet. You can refine your modelling by optionally changing your spending profile, your estimation of inflation , triple-lock and also selecting your inflation tracking mode Further details are available in these accompanying videos. Enjoy exploring your future — it's all in your hands!
B5: - Video 1 - Video 2 - Video 3
B6: Assumptions: We assume that you are drawing down from either a FAD or UFPLS drawdown SIPP at a taxable rate of 75% / 25% (taxable/taxfree) Need more here ...

Sheet Income
B1: Pensions and other income
B2: Person 1 | I2: Person 2
D3: Value | E3: Growth Rate | F3: Year | G3: Pre-retirement savings, annual | K3: Value | L3: Growth Rate | M3: Year | N3: Pre-retirement savings, annual
B4: SIPP Total | D4: 990000 | E4: 0.065 | G4: 0 | I4: SIPP Total | K4: 0 | L4: 0 | N4: 0
B6: Annuity 1 | D6: 0 | E6: NA | I6: Annuity 1 | K6: 0 | L6: NA | M6: 0
B7: Annuity 2 | D7: 0 | E7: NA | I7: Annuity 2 | K7: 0 | L7: NA
B8: Annuity 3 | D8: 0 | E8: NA | I8: Annuity 3 | K8: 0 | L8: NA
B10: Defined Benefit Pension 1 | D10: 0 | E10: NA | F10: 2026 | I10: Defined Benefit Pension 1 | K10: 7000 | L10: NA | M10: 2026
B11: Defined Benefit Pension 2 | D11: 0 | E11: NA | I11: Defined Benefit Pension 2 | K11: 3000 | L11: NA | M11: 2030
B12: Defined Benefit Pension 3 | D12: 0 | E12: NA | I12: Defined Benefit Pension 3 | K12: 0 | L12: NA
F13: Draw-down | M13: Draw-down
B14: Cash ISA | D14: 20000 | E14: 0.038 | F14: =calculateAnnualDrawdown('Person 1 Calculator'!$F$4, D14, E14, 'Person 1 Calculator'!$F$5-'Person 1 Calculator'!$F$4, G14) -> 636.62 | G14: 0 | I14: Cash ISA | K14: 20000 | L14: 0.038 | M14: =calculateAnnualDrawdown('Person 1 Calculator'!$F$4, K14, L14, 'Person 1 Calculator'!$F$5-'Person 1 Calculator'!$F$4, N14) -> 636.62 | N14: 0
B15: Stocks & Shares ISA | D15: 250000 | E15: 0.065 | F15: =calculateAnnualDrawdown('Person 1 Calculator'!$F$4, D15, E15, 'Person 1 Calculator'!$F$5-'Person 1 Calculator'!$F$4, G15) -> 8062.48 | G15: 0 | I15: Stocks & Shares ISA | K15: 200000 | L15: 0.065 | M15: =calculateAnnualDrawdown('Person 1 Calculator'!$F$4, K15, L15, 'Person 1 Calculator'!$F$5-'Person 1 Calculator'!$F$4, N15) -> 6449.99 | N15: 0
B16: Cash | D16: 50000 | E16: 0.065 | F16: =calculateAnnualDrawdown('Person 1 Calculator'!$F$4, D16, E16, 'Person 1 Calculator'!$F$5-'Person 1 Calculator'!$F$4, G16) -> 1612.5 | G16: 0 | I16: Cash | K16: 150000 | L16: 0.065 | M16: =calculateAnnualDrawdown('Person 1 Calculator'!$F$4, K16, L16, 'Person 1 Calculator'!$F$5-'Person 1 Calculator'!$F$4, N16) -> 4837.49 | N16: 0
B18: Starting rent (Net) | D18: 20000 | E18: 0.025 | I18: Starting rent (Net) | K18: 0 | L18: 0.025
B20: State Pension Eligibility @ Projected Retirement Age | F20: 1 | I20: State Pension Eligibility @ Projected Retirement Age | M20: 1
B21: State Pension @ 67 | D21: =fv('Person 1 Calculator'!$F$19,'Person 1 Calculator'!$F$7-year(today()),0,-(F20*(52*230.25))) -> 17722.965 | I21: State Pension @ 67 | K21: =fv('Person 2 Calculator'!$F$19,'Person 2 Calculator'!$F$7-year(today()),0,-(M20*(52*230.25))) -> 18431.883

Sheet Person 1 Calculator
B1: Person 1 Pension Calculator
B2: Parameters | H2: Income Performance
B3: Year of Birth | F3: 1968
B4: Start Draw-down In | F4: 2026
B5: End Draw-down By | F5: 2058
B6: Private Pension Eligible Year (age 55) | F6: =F3+55 -> 2023
B7: State Pension Eligible Year | F7: =F3+67 -> 2035
B8: Final Year Percentage (keep hidden)
B9: First Year Estimated Income | C9: Net | D9: ='Person 1 Draw-down'!G32 -> 89085.252 | E9: | Gross | F9: 108669.67
B10: Estimated Income @ 70 | C10: Net Real | D10: ='Person 1 Draw-down'!S27*$D$9 -> 71268.202 | E10: | Nominal Gross | F10: ='Person 1 Draw-down'!S24 -> 116918.9
B11: Estimated Income @ 80 | C11: Net Real | D11: ='Person 1 Draw-down'!AC27*$D$9 -> 53451.151 | E11: | Nominal Gross | F11: ='Person 1 Draw-down'!AC24 -> 112249.56
B12: Final Year Estimated Income | C12: Net Real | D12: ='Person 1 Draw-down'!AL27*$D$9 -> 53451.151 | E12: | Nominal Gross | F12: ='Person 1 Draw-down'!AL24 -> 140184.32
B13: Final Year SIPP Balance Target | F13: 0
B14: Final Year SIPP Balance | F14: ='Person 1 Draw-down'!AL6 -> 0.38076382
B16: Optional annual spending reduction from age 70 | F16: 0.2
B17: Optional annual spending reduction from age 80 | F17: 0.4
B18: Inflation | F18: 0.025
B19: State Pension Growth (triple-lock) | F19: 0.04
B20: Inflation tracking mode | F20: Smooth

Sheet Person 1 Draw-down
A1: Pension 1 Draw-down
A3: Age | D3: 55 | E3: 56 | F3: 57 | G3: 58 | H3: 59 | I3: 60 | J3: 61 | K3: 62 | L3: 63 | M3: 64 | N3: 65 | O3: 66 | P3: 67 | Q3: 68 | R3: 69 | S3: 70 | T3: 71 | U3: 72 | V3: 73 | W3: 74 | X3: 75 | Y3: 76 | Z3: 77 | AA3: 78 | AB3: 79 | AC3: 80 | AD3: 81 | AE3: 82 | AF3: 83 | AG3: 84 | AH3: 85 | AI3: 86 | AJ3: 87 | AK3: 88 | AL3: 89 | AM3: 90 | AN3: 91 | AO3: 92 | AP3: 93 | AQ3: 94 | AR3: 95 | AS3: 96 | AT3: 97 | AU3: 98 | AV3: 99
A4: Year | D4: ='Person 1 Calculator'!$F$6 -> 2023 | E4: =D4+1 -> 2024 | F4: =E4+1 -> 2025 | G4: =F4+1 -> 2026 | H4: =G4+1 -> 2027 | I4: =H4+1 -> 2028 | J4: =I4+1 -> 2029 | K4: =J4+1 -> 2030 | L4: =K4+1 -> 2031 | ... AV4: =AU4+1 -> 2067
A5: ONGOING ASSET VALUES | D5: =LET( TargetYear, D4, StartDate, 'Person 1 Calculator'!$F$4, EndDate, 'Person 1 Calculator'!$F$5, IFS( TargetYear < StartDate, 0, TargetYear = StartDate, 1, AND(TargetYear > StartDate, TargetYear < EndDate), 2, TargetYear >= EndDate, 3 ) ) -> 0 | E5: =LET( TargetYear, E4, StartDate, 'Person 1 Calculator'!$F$4, EndDate, 'Person 1 Calculator'!$F$5, IFS( TargetYear < StartDate, 0, TargetYear = StartDate, 1, AND(TargetYear > StartDate, TargetYear < EndDate), 2, TargetYear >= EndDate, 3 ) ) -> 0 | F5: =LET( TargetYear, F4, StartDate, 'Person 1 Calculator'!$F$4, EndDate, 'Person 1 Calculator'!$F$5, IFS( TargetYear < StartDate, 0, TargetYear = StartDate, 1, AND(TargetYear > StartDate, TargetYear < EndDate), 2, TargetYear >= EndDate, 3 ) ) -> 0 | G5: =LET( TargetYear, G4, StartDate, 'Person 1 Calculator'!$F$4, EndDate, 'Person 1 Calculator'!$F$5, IFS( TargetYear < StartDate, 0, TargetYear = StartDate, 1, AND(TargetYear > StartDate, TargetYear < EndDate), 2, TargetYear >= EndDate, 3 ) ) -> 1 | H5: =LET( TargetYear, H4, StartDate, 'Person 1 Calculator'!$F$4, EndDate, 'Person 1 Calculator'!$F$5, IFS( TargetYear < StartDate, 0, TargetYear = StartDate, 1, AND(TargetYear > StartDate, TargetYear < EndDate), 2, TargetYear >= EndDate, 3 ) ) -> 2 | I5: =LET( TargetYear, I4, StartDate, 'Person 1 Calculator'!$F$4, EndDate, 'Person 1 Calculator'!$F$5, IFS( TargetYear < StartDate, 0, TargetYear = StartDate, 1, AND(TargetYear > StartDate, TargetYear < EndDate), 2, TargetYear >= EndDate, 3 ) ) -> 2 | J5: =LET( TargetYear, J4, StartDate, 'Person 1 Calculator'!$F$4, EndDate, 'Person 1 Calculator'!$F$5, IFS( TargetYear < StartDate, 0, TargetYear = StartDate, 1, AND(TargetYear > StartDate, TargetYear < EndDate), 2, TargetYear >= EndDate, 3 ) ) -> 2 | K5: =LET( TargetYear, K4, StartDate, 'Person 1 Calculator'!$F$4, EndDate, 'Person 1 Calculator'!$F$5, IFS( TargetYear < StartDate, 0, TargetYear = StartDate, 1, AND(TargetYear > StartDate, TargetYear < EndDate), 2, TargetYear >= EndDate, 3 ) ) -> 2 | ... AV5: =LET( TargetYear, AV4, StartDate, 'Person 1 Calculator'!$F$4, EndDate, 'Person 1 Calculator'!$F$5, IFS( TargetYear < StartDate, 0, TargetYear = StartDate, 1, AND(TargetYear > StartDate, TargetYear < EndDate), 2, TargetYear >= EndDate, 3 ) ) -> 3
A6: SIPP Value | D6: =LET( CurrentYear, D4, PreviousYearValue, C6, ActionCode, N(D5), DeductionAmount, D7, InitialSeedValue, Income!$D$4, AnnualGrowthRate, Income!$E$4, FixedAnnualAddition, Income!$G$4, CalculationValue, IF(N(PreviousYearValue)=0, InitialSeedValue, PreviousYearValue), ProrataFactor, IF(CurrentYear = YEAR(TODAY()), (12 - MONTH(TODAY()) + 1) / 12, 1), GrowthAmount, CalculationValue * AnnualGrowthRate, IsYearInPast, CurrentYear < YEAR(TODAY()), IsStopCode, ActionCode = 3, IF(OR(IsYearInPast, IsStopCode), "", SWITCH(ActionCode, 0, CalculationValue + (GrowthAmount + FixedAnnualAddition) * ProrataFactor, 1, CalculationValue + (GrowthAmount - DeductionAmount) * ProrataFactor, 2, CalculationValue + (GrowthAmount - DeductionAmount) * ProrataFactor, "" ) ) ) | E6: =if(D6<0,D6, LET( CurrentYear, E4, PreviousYearValue, D6, ActionCode, N(E5), DeductionAmount, E7, InitialSeedValue, Income!$D$4, AnnualGrowthRate, Income!$E$4, FixedAnnualAddition, Income!$G$4, CalculationValue, IF(N(PreviousYearValue)=0, InitialSeedValue, PreviousYearValue), ProrataFactor, IF(CurrentYear = YEAR(TODAY()), (12 - MONTH(TODAY()) + 1) / 12, 1), GrowthAmount, CalculationValue * AnnualGrowthRate, IsYearInPast, CurrentYear < YEAR(TODAY()), IsStopCode, ActionCode = 3, IF(OR(IsYearInPast, IsStopCode), "", SWITCH(ActionCode, 0, CalculationValue + (GrowthAmount + FixedAnnualAddition) * ProrataFactor, 1, CalculationValue + (GrowthAmount - DeductionAmount) * ProrataFactor, 2, CalculationValue + (GrowthAmount - DeductionAmount) * ProrataFactor, "" ) ) ) ) | F6: =if(E6<0,E6, LET( CurrentYear, F4, PreviousYearValue, E6, ActionCode, N(F5), DeductionAmount, F7, InitialSeedValue, Income!$D$4, AnnualGrowthRate, Income!$E$4, FixedAnnualAddition, Income!$G$4, CalculationValue, IF(N(PreviousYearValue)=0, InitialSeedValue, PreviousYearValue), ProrataFactor, IF(CurrentYear = YEAR(TODAY()), (12 - MONTH(TODAY()) + 1) / 12, 1), GrowthAmount, CalculationValue * AnnualGrowthRate, IsYearInPast, CurrentYear < YEAR(TODAY()), IsStopCode, ActionCode = 3, IF(OR(IsYearInPast, IsStopCode), "", SWITCH(ActionCode, 0, CalculationValue + (GrowthAmount + FixedAnnualAddition) * ProrataFactor, 1, CalculationValue + (GrowthAmount - DeductionAmount) * ProrataFactor, 2, CalculationValue + (GrowthAmount - DeductionAmount) * ProrataFactor, "" ) ) ) ) -> 1000725 | G6: =if(F6<0,F6, LET( CurrentYear, G4, PreviousYearValue, F6, ActionCode, N(G5), DeductionAmount, G7, InitialSeedValue, Income!$D$4, AnnualGrowthRate, Income!$E$4, FixedAnnualAddition, Income!$G$4, CalculationValue, IF(N(PreviousYearValue)=0, InitialSeedValue, PreviousYearValue), ProrataFactor, IF(CurrentYear = YEAR(TODAY()), (12 - MONTH(TODAY()) + 1) / 12, 1), GrowthAmount, CalculationValue * AnnualGrowthRate, IsYearInPast, CurrentYear < YEAR(TODAY()), IsStopCode, ActionCode = 3, IF(OR(IsYearInPast, IsStopCode), "", SWITCH(ActionCode, 0, CalculationValue + (GrowthAmount + FixedAnnualAddition) * ProrataFactor, 1, CalculationValue + (GrowthAmount - DeductionAmount) * ProrataFactor, 2, CalculationValue + (GrowthAmount - DeductionAmount) * ProrataFactor, "" ) ) ) ) -> 987414.05 | H6: =if(G6<0,G6, LET( CurrentYear, H4, PreviousYearValue, G6, ActionCode, N(H5), DeductionAmount, H7, InitialSeedValue, Income!$D$4, AnnualGrowthRate, Income!$E$4, FixedAnnualAddition, Income!$G$4, CalculationValue, IF(N(PreviousYearValue)=0, InitialSeedValue, PreviousYearValue), ProrataFactor, IF(CurrentYear = YEAR(TODAY()), (12 - MONTH(TODAY()) + 1) / 12, 1), GrowthAmount, CalculationValue * AnnualGrowthRate, IsYearInPast, CurrentYear < YEAR(TODAY()), IsStopCode, ActionCode = 3, IF(OR(IsYearInPast, IsStopCode), "", SWITCH(ActionCode, 0, CalculationValue + (GrowthAmount + FixedAnnualAddition) * ProrataFactor, 1, CalculationValue + (GrowthAmount - DeductionAmount) * ProrataFactor, 2, CalculationValue + (GrowthAmount - DeductionAmount) * ProrataFactor, "" ) ) ) ) -> 971021.15 | I6: =if(H6<0,H6, LET( CurrentYear, I4, PreviousYearValue, H6, ActionCode, N(I5), DeductionAmount, I7, InitialSeedValue, Income!$D$4, AnnualGrowthRate, Income!$E$4, FixedAnnualAddition, Income!$G$4, CalculationValue, IF(N(PreviousYearValue)=0, InitialSeedValue, PreviousYearValue), ProrataFactor, IF(CurrentYear = YEAR(TODAY()), (12 - MONTH(TODAY()) + 1) / 12, 1), GrowthAmount, CalculationValue * AnnualGrowthRate, IsYearInPast, CurrentYear < YEAR(TODAY()), IsStopCode, ActionCode = 3, IF(OR(IsYearInPast, IsStopCode), "", SWITCH(ActionCode, 0, CalculationValue + (GrowthAmount + FixedAnnualAddition) * ProrataFactor, 1, CalculationValue + (GrowthAmount - DeductionAmount) * ProrataFactor, 2, CalculationValue + (GrowthAmount - DeductionAmount) * ProrataFactor, "" ) ) ) ) -> 951290.54 | J6: =if(I6<0,I6, LET( CurrentYear, J4, PreviousYearValue, I6, ActionCode, N(J5), DeductionAmount, J7, InitialSeedValue, Income!$D$4, AnnualGrowthRate, Income!$E$4, FixedAnnualAddition, Income!$G$4, CalculationValue, IF(N(PreviousYearValue)=0, InitialSeedValue, PreviousYearValue), ProrataFactor, IF(CurrentYear = YEAR(TODAY()), (12 - MONTH(TODAY()) + 1) / 12, 1), GrowthAmount, CalculationValue * AnnualGrowthRate, IsYearInPast, CurrentYear < YEAR(TODAY()), IsStopCode, ActionCode = 3, IF(OR(IsYearInPast, IsStopCode), "", SWITCH(ActionCode, 0, CalculationValue + (GrowthAmount + FixedAnnualAddition) * ProrataFactor, 1, CalculationValue + (GrowthAmount - DeductionAmount) * ProrataFactor, 2, CalculationValue + (GrowthAmount - DeductionAmount) * ProrataFactor, "" ) ) ) ) -> 927948.49 | K6: =if(J6<0,J6, LET( CurrentYear, K4, PreviousYearValue, J6, ActionCode, N(K5), DeductionAmount, K7, InitialSeedValue, Income!$D$4, AnnualGrowthRate, Income!$E$4, FixedAnnualAddition, Income!$G$4, CalculationValue, IF(N(PreviousYearValue)=0, InitialSeedValue, PreviousYearValue), ProrataFactor, IF(CurrentYear = YEAR(TODAY()), (12 - MONTH(TODAY()) + 1) / 12, 1), GrowthAmount, CalculationValue * AnnualGrowthRate, IsYearInPast, CurrentYear < YEAR(TODAY()), IsStopCode, ActionCode = 3, IF(OR(IsYearInPast, IsStopCode), "", SWITCH(ActionCode, 0, CalculationValue + (GrowthAmount + FixedAnnualAddition) * ProrataFactor, 1, CalculationValue + (GrowthAmount - DeductionAmount) * ProrataFactor, 2, CalculationValue + (GrowthAmount - DeductionAmount) * ProrataFactor, "" ) ) ) ) -> 900702.01 | L6: =if(K6<0,K6, LET( CurrentYear, L4, PreviousYearValue, K6, ActionCode, N(L5), DeductionAmount, L7, InitialSeedValue, Income!$D$4, AnnualGrowthRate, Income!$E$4, FixedAnnualAddition, Income!$G$4, CalculationValue, IF(N(PreviousYearValue)=0, InitialSeedValue, PreviousYearValue), ProrataFactor, IF(CurrentYear = YEAR(TODAY()), (12 - MONTH(TODAY()) + 1) / 12, 1), GrowthAmount, CalculationValue * AnnualGrowthRate, IsYearInPast, CurrentYear < YEAR(TODAY()), IsStopCode, ActionCode = 3, IF(OR(IsYearInPast, IsStopCode), "", SWITCH(ActionCode, 0, CalculationValue + (GrowthAmount + FixedAnnualAddition) * ProrataFactor, 1, CalculationValue + (GrowthAmount - DeductionAmount) * ProrataFactor, 2, CalculationValue + (GrowthAmount - DeductionAmount) * ProrataFactor, "" ) ) ) ) -> 869237.64 | ... AV6: =if(AU6<0,AU6, LET( CurrentYear, AV4, PreviousYearValue, AU6, ActionCode, N(AV5), DeductionAmount, AV7, InitialSeedValue, Income!$D$4, AnnualGrowthRate, Income!$E$4, FixedAnnualAddition, Income!$G$4, CalculationValue, IF(N(PreviousYearValue)=0, InitialSeedValue, PreviousYearValue), ProrataFactor, IF(CurrentYear = YEAR(TODAY()), (12 - MONTH(TODAY()) + 1) / 12, 1), GrowthAmount, CalculationValue * AnnualGrowthRate, IsYearInPast, CurrentYear < YEAR(TODAY()), IsStopCode, ActionCode = 3, IF(OR(IsYearInPast, IsStopCode), "", SWITCH(ActionCode, 0, CalculationValue + (GrowthAmount + FixedAnnualAddition) * ProrataFactor, 1, CalculationValue + (GrowthAmount - DeductionAmount) * ProrataFactor, 2, CalculationValue + (GrowthAmount - DeductionAmount) * ProrataFactor, "" ) ) ) )
A7: Annual SIPP Draw-down | D7: =IF(OR(D5=1, D5=2), D26-D12-D14-D16-D18-D20-D22, ) | E7: =LET( base, E26 - E12 - E14 - E16 - E18 - E20 - E22, IFS( E5 = 0, "", E5 = 1, base, E5 = 2, IF( ISNUMBER(SEARCH("Smooth", 'Person 1 Calculator'!$F$20)), MAX(base, 0), D7 ), E5 = 3, "" ) ) | F7: =LET( base, F26 - F12 - F14 - F16 - F18 - F20 - F22, IFS( F5 = 0, "", F5 = 1, base, F5 = 2, IF( ISNUMBER(SEARCH("Smooth", 'Person 1 Calculator'!$F$20)), MAX(base, 0), E7 ), F5 = 3, "" ) ) | G7: =LET( base, G26 - G12 - G14 - G16 - G18 - G20 - G22, IFS( G5 = 0, "", G5 = 1, base, G5 = 2, IF( ISNUMBER(SEARCH("Smooth", 'Person 1 Calculator'!$F$20)), MAX(base, 0), F7 ), G5 = 3, "" ) ) -> 78358.075 | H7: =LET( base, H26 - H12 - H14 - H16 - H18 - H20 - H22, IFS( H5 = 0, "", H5 = 1, base, H5 = 2, IF( ISNUMBER(SEARCH("Smooth", 'Person 1 Calculator'!$F$20)), MAX(base, 0), G7 ), H5 = 3, "" ) ) -> 80574.817 | I7: =IF(OR(I5=1, I5=2), I26-I12-I14-I16-I18-I20-I22, ) -> 82846.977 | J7: =LET( base, J26 - J12 - J14 - J16 - J18 - J20 - J22, IFS( J5 = 0, "", J5 = 1, base, J5 = 2, IF( ISNUMBER(SEARCH("Smooth", 'Person 1 Calculator'!$F$20)), MAX(base, 0), I7 ), J5 = 3, "" ) ) -> 85175.942 | K7: =LET( base, K26 - K12 - K14 - K16 - K18 - K20 - K22, IFS( K5 = 0, "", K5 = 1, base, K5 = 2, IF( ISNUMBER(SEARCH("Smooth", 'Person 1 Calculator'!$F$20)), MAX(base, 0), J7 ), K5 = 3, "" ) ) -> 87563.13 | L7: =LET( base, L26 - L12 - L14 - L16 - L18 - L20 - L22, IFS( L5 = 0, "", L5 = 1, base, L5 = 2, IF( ISNUMBER(SEARCH("Smooth", 'Person 1 Calculator'!$F$20)), MAX(base, 0), K7 ), L5 = 3, "" ) ) -> 90009.998 | M7: =LET( base, M26 - M12 - M14 - M16 - M18 - M20 - M22, IFS( M5 = 0, "", M5 = 1, base, M5 = 2, IF( ISNUMBER(SEARCH("Smooth", 'Person 1 Calculator'!$F$20)), MAX(base, 0), L7 ), M5 = 3, "" ) ) -> 92518.038 | N7: =IF(OR(N5=1, N5=2), N26-N12-N14-N16-N18-N20-N22, ) -> 95088.779 | O7: =LET( base, O26 - O12 - O14 - O16 - O18 - O20 - O22, IFS( O5 = 0, "", O5 = 1, base, O5 = 2, IF( ISNUMBER(SEARCH("Smooth", 'Person 1 Calculator'!$F$20)), MAX(base, 0), N7 ), O5 = 3, "" ) ) -> 97723.789 | P7: =LET( base, P26 - P12 - P14 - P16 - P18 - P20 - P22, raw, IFS( P5 = 0, "", P5 = 1, base, P5 = 2, IF( ISNUMBER(SEARCH("Smooth", 'Person 1 Calculator'!$F$20)), base, O7 - P16 ), P5 = 3, "" ), IF(ISNUMBER(raw), MAX(raw, 0), raw) ) -> 82701.709 | Q7: =LET( base, Q26 - Q12 - Q14 - Q16 - Q18 - Q20 - Q22, IFS( Q5 = 0, "", Q5 = 1, base, Q5 = 2, IF( ISNUMBER(SEARCH("Smooth", 'Person 1 Calculator'!$F$20)), MAX(base, 0), P7 ), Q5 = 3, "" ) ) -> 84761.197 | R7: =LET( base, R26 - R12 - R14 - R16 - R18 - R20 - R22, IFS( R5 = 0, "", R5 = 1, base, R5 = 2, IF( ISNUMBER(SEARCH("Smooth", 'Person 1 Calculator'!$F$20)), MAX(base, 0), Q7 ), R5 = 3, "" ) ) -> 86861.539 | S7: =IF( OR(S5 = 1, S5 = 2), MAX(0, (1-'Person 1 Calculator'!$F$16)*S26 - S12 - S14 - S16 - S18 - S20 - S22), "" ) -> 59773.603 | T7: =LET( base, (1-'Person 1 Calculator'!$F$16)*T26 - T12 - T14 - T16 - T18 - T20 - T22, IFS( T5 = 0, "", T5 = 1, base, T5 = 2, IF( ISNUMBER(SEARCH("Smooth", 'Person 1 Calculator'!$F$20)), MAX(base, 0), S7 ), T5 = 3, "" ) ) -> 61226.695 | U7: =LET( base, (1-'Person 1 Calculator'!$F$16)*U26 - U12 - U14 - U16 - U18 - U20 - U22, IFS( U5 = 0, "", U5 = 1, base, U5 = 2, IF( ISNUMBER(SEARCH("Smooth", 'Person 1 Calculator'!$F$20)), MAX(base, 0), T7 ), U5 = 3, "" ) ) -> 62704.152 | V7: =LET( base, (1-'Person 1 Calculator'!$F$16)*V26 - V12 - V14 - V16 - V18 - V20 - V22, IFS( V5 = 0, "", V5 = 1, base, V5 = 2, IF( ISNUMBER(SEARCH("Smooth", 'Person 1 Calculator'!$F$20)), MAX(base, 0), U7 ), V5 = 3, "" ) ) -> 64206.105 | W7: =LET( base, (1-'Person 1 Calculator'!$F$16)*W26 - W12 - W14 - W16 - W18 - W20 - W22, IFS( W5 = 0, "", W5 = 1, base, W5 = 2, IF( ISNUMBER(SEARCH("Smooth", 'Person 1 Calculator'!$F$20)), MAX(base, 0), V7 ), W5 = 3, "" ) ) -> 65732.669 | X7: =IF( OR(X5 = 1, X5 = 2), MAX(0, (1-'Person 1 Calculator'!$F$16)*X26 - X12 - X14 - X16 - X18 - X20 - X22), "" ) -> 67283.943 | Y7: =LET( base, (1-'Person 1 Calculator'!$F$16)*Y26 - Y12 - Y14 - Y16 - Y18 - Y20 - Y22, IFS( Y5 = 0, "", Y5 = 1, base, Y5 = 2, IF( ISNUMBER(SEARCH("Smooth", 'Person 1 Calculator'!$F$20)), MAX(base, 0), X7 ), Y5 = 3, "" ) ) -> 68860.005 | Z7: =LET( base, (1-'Person 1 Calculator'!$F$16)*Z26 - Z12 - Z14 - Z16 - Z18 - Z20 - Z22, IFS( Z5 = 0, "", Z5 = 1, base, Z5 = 2, IF( ISNUMBER(SEARCH("Smooth", 'Person 1 Calculator'!$F$20)), MAX(base, 0), Y7 ), Z5 = 3, "" ) ) -> 70460.916 | AA7: =LET( base, (1-'Person 1 Calculator'!$F$16)*AA26 - AA12 - AA14 - AA16 - AA18 - AA20 - AA22, IFS( AA5 = 0, "", AA5 = 1, base, AA5 = 2, IF( ISNUMBER(SEARCH("Smooth", 'Person 1 Calculator'!$F$20)), MAX(base, 0), Z7 ), AA5 = 3, "" ) ) -> 72086.714 | AB7: =LET( base, (1-'Person 1 Calculator'!$F$16)*AB26 - AB12 - AB14 - AB16 - AB18 - AB20 - AB22, IFS( AB5 = 0, "", AB5 = 1, base, AB5 = 2, IF( ISNUMBER(SEARCH("Smooth", 'Person 1 Calculator'!$F$20)), MAX(base, 0), AA7 ), AB5 = 3, "" ) ) -> 73737.416 | AC7: =IF( OR(AC5 = 1, AC5 = 2), MAX(0, (1-'Person 1 Calculator'!$F$17)*AC26 - AC12 - AC14 - AC16 - AC18 - AC20 - AC22), "" ) -> 37996.495 | AD7: =LET( base, (1-'Person 1 Calculator'!$F$17)*AD26 - AD12 - AD14 - AD16 - AD18 - AD20 - AD22, IFS( AD5 = 0, "", AD5 = 1, base, AD5 = 2, IF( ISNUMBER(SEARCH("Smooth", 'Person 1 Calculator'!$F$20)), MAX(base, 0), AC7 ), AD5 = 3, "" ) ) -> 38761.547 | AE7: =LET( base, (1-'Person 1 Calculator'!$F$17)*AE26 - AE12 - AE14 - AE16 - AE18 - AE20 - AE22, IFS( AE5 = 0, "", AE5 = 1, base, AE5 = 2, IF( ISNUMBER(SEARCH("Smooth", 'Person 1 Calculator'!$F$20)), MAX(base, 0), AD7 ), AE5 = 3, "" ) ) -> 39528.019 | AF7: =LET( base, (1-'Person 1 Calculator'!$F$17)*AF26 - AF12 - AF14 - AF16 - AF18 - AF20 - AF22, IFS( AF5 = 0, "", AF5 = 1, base, AF5 = 2, IF( ISNUMBER(SEARCH("Smooth", 'Person 1 Calculator'!$F$20)), MAX(base, 0), AE7 ), AF5 = 3, "" ) ) -> 40295.239 | AG7: =LET( base, (1-'Person 1 Calculator'!$F$17)*AG26 - AG12 - AG14 - AG16 - AG18 - AG20 - AG22, IFS( AG5 = 0, "", AG5 = 1, base, AG5 = 2, IF( ISNUMBER(SEARCH("Smooth", 'Person 1 Calculator'!$F$20)), MAX(base, 0), AF7 ), AG5 = 3, "" ) ) -> 41062.488 | AH7: =IF( OR(AH5 = 1, AH5 = 2), MAX(0, (1-'Person 1 Calculator'!$F$17)*AH26 - AH12 - AH14 - AH16 - AH18 - AH20 - AH22), "" ) -> 41829.002 | AI7: =LET( base, (1-'Person 1 Calculator'!$F$17)*AI26 - AI12 - AI14 - AI16 - AI18 - AI20 - AI22, IFS( AI5 = 0, "", AI5 = 1, base, AI5 = 2, IF( ISNUMBER(SEARCH("Smooth", 'Person 1 Calculator'!$F$20)), MAX(base, 0), AH7 ), AI5 = 3, "" ) ) -> 42593.965 | AJ7: =LET( base, (1-'Person 1 Calculator'!$F$17)*AJ26 - AJ12 - AJ14 - AJ16 - AJ18 - AJ20 - AJ22, IFS( AJ5 = 0, "", AJ5 = 1, base, AJ5 = 2, IF( ISNUMBER(SEARCH("Smooth", 'Person 1 Calculator'!$F$20)), MAX(base, 0), AI7 ), AJ5 = 3, "" ) ) -> 43356.509 | AK7: =LET( base, (1-'Person 1 Calculator'!$F$17)*AK26 - AK12 - AK14 - AK16 - AK18 - AK20 - AK22, IFS( AK5 = 0, "", AK5 = 1, base, AK5 = 2, IF( ISNUMBER(SEARCH("Smooth", 'Person 1 Calculator'!$F$20)), MAX(base, 0), AJ7 ), AK5 = 3, "" ) ) -> 44115.714 | AL7: =LET( base, (1-'Person 1 Calculator'!$F$17)*AL26 - AL12 - AL14 - AL16 - AL18 - AL20 - AL22, IFS( AL5 = 0, "", AL5 = 1, base, AL5 = 2, IF( ISNUMBER(SEARCH("Smooth", 'Person 1 Calculator'!$F$20)), MAX(base, 0), AK7 ), AL5 = 3, "" ) ) -> 44870.599 | AM7: =IF( OR(AM5 = 1, AM5 = 2), MAX(0, (1-'Person 1 Calculator'!$F$17)*AM26 - AM12 - AM14 - AM16 - AM18 - AM20 - AM22), "" ) | AN7: =LET( base, (1-'Person 1 Calculator'!$F$17)*AN26 - AN12 - AN14 - AN16 - AN18 - AN20 - AN22, IFS( AN5 = 0, "", AN5 = 1, base, AN5 = 2, IF( ISNUMBER(SEARCH("Smooth", 'Person 1 Calculator'!$F$20)), MAX(base, 0), AM7 ), AN5 = 3, "" ) ) | AO7: =LET( base, (1-'Person 1 Calculator'!$F$17)*AO26 - AO12 - AO14 - AO16 - AO18 - AO20 - AO22, IFS( AO5 = 0, "", AO5 = 1, base, AO5 = 2, IF( ISNUMBER(SEARCH("Smooth", 'Person 1 Calculator'!$F$20)), MAX(base, 0), AN7 ), AO5 = 3, "" ) ) | AP7: =LET( base, (1-'Person 1 Calculator'!$F$17)*AP26 - AP12 - AP14 - AP16 - AP18 - AP20 - AP22, IFS( AP5 = 0, "", AP5 = 1, base, AP5 = 2, IF( ISNUMBER(SEARCH("Smooth", 'Person 1 Calculator'!$F$20)), MAX(base, 0), AO7 ), AP5 = 3, "" ) ) | AQ7: =LET( base, (1-'Person 1 Calculator'!$F$17)*AQ26 - AQ12 - AQ14 - AQ16 - AQ18 - AQ20 - AQ22, IFS( AQ5 = 0, "", AQ5 = 1, base, AQ5 = 2, IF( ISNUMBER(SEARCH("Smooth", 'Person 1 Calculator'!$F$20)), MAX(base, 0), AP7 ), AQ5 = 3, "" ) ) | AR7: =IF( OR(AR5 = 1, AR5 = 2), MAX(0, (1-'Person 1 Calculator'!$F$17)*AR26 - AR12 - AR14 - AR16 - AR18 - AR20 - AR22), "" ) | AS7: =LET( base, (1-'Person 1 Calculator'!$F$17)*AS26 - AS12 - AS14 - AS16 - AS18 - AS20 - AS22, IFS( AS5 = 0, "", AS5 = 1, base, AS5 = 2, IF( ISNUMBER(SEARCH("Smooth", 'Person 1 Calculator'!$F$20)), MAX(base, 0), AR7 ), AS5 = 3, "" ) ) | AT7: =LET( base, (1-'Person 1 Calculator'!$F$17)*AT26 - AT12 - AT14 - AT16 - AT18 - AT20 - AT22, IFS( AT5 = 0, "", AT5 = 1, base, AT5 = 2, IF( ISNUMBER(SEARCH("Smooth", 'Person 1 Calculator'!$F$20)), MAX(base, 0), AS7 ), AT5 = 3, "" ) ) | AU7: =LET( base, (1-'Person 1 Calculator'!$F$17)*AU26 - AU12 - AU14 - AU16 - AU18 - AU20 - AU22, IFS( AU5 = 0, "", AU5 = 1, base, AU5 = 2, IF( ISNUMBER(SEARCH("Smooth", 'Person 1 Calculator'!$F$20)), MAX(base, 0), AT7 ), AU5 = 3, "" ) ) | AV7: =LET( base, (1-'Person 1 Calculator'!$F$17)*AV26 - AV12 - AV14 - AV16 - AV18 - AV20 - AV22, IFS( AV5 = 0, "", AV5 = 1, base, AV5 = 2, IF( ISNUMBER(SEARCH("Smooth", 'Person 1 Calculator'!$F$20)), MAX(base, 0), AU7 ), AV5 = 3, "" ) )
A8: Taxable draw-down (75%) | D8: =if(N(D7)>0,D7*0.75,) | E8: =if(N(E7)>0,E7*0.75,) | F8: =if(N(F7)>0,F7*0.75,) | G8: =if(N(G7)>0,G7*0.75,) -> 58768.556 | H8: =if(N(H7)>0,H7*0.75,) -> 60431.113 | I8: =if(N(I7)>0,I7*0.75,) -> 62135.233 | J8: =if(N(J7)>0,J7*0.75,) -> 63881.956 | K8: =if(N(K7)>0,K7*0.75,) -> 65672.348 | ... AV8: =if(N(AV7)>0,AV7*0.75,)
A9: Tax-free draw-down (25%) | D9: =if(N(D7)>0,D7*0.25,) | E9: =if(N(E7)>0,E7*0.25,) | F9: =if(N(F7)>0,F7*0.25,) | G9: =if(N(G7)>0,G7*0.25,) -> 19589.519 | H9: =if(N(H7)>0,H7*0.25,) -> 20143.704 | I9: =if(N(I7)>0,I7*0.25,) -> 20711.744 | J9: =if(N(J7)>0,J7*0.25,) -> 21293.985 | K9: =if(N(K7)>0,K7*0.25,) -> 21890.783 | ... AV9: =if(N(AV7)>0,AV7*0.25,)
A10: Accumulated tax free draw-down | D10: =D9 | E10: =if(OR(E5=1,E5=2),D10+E9,) | F10: =if(OR(F5=1,F5=2),E10+F9,) | G10: =if(OR(G5=1,G5=2),F10+G9,) -> 19589.519 | H10: =if(OR(H5=1,H5=2),G10+H9,) -> 39733.223 | I10: =if(OR(I5=1,I5=2),H10+I9,) -> 60444.967 | J10: =if(OR(J5=1,J5=2),I10+J9,) -> 81738.953 | K10: =if(OR(K5=1,K5=2),J10+K9,) -> 103629.74 | L10: =if(OR(L5=1,L5=2),K10+L9,) -> 126132.23 | ... AV10: =if(OR(AV5=1,AV5=2),AU10+AV9,)
A11: Monthly SIPP draw-down | D11: =if(N(D7)>0,D7/12,) | E11: =if(N(E7)>0,E7/12,) | F11: =if(N(F7)>0,F7/12,) | G11: =if(N(G7)>0,G7/12,) -> 6529.8396 | H11: =if(N(H7)>0,H7/12,) -> 6714.5681 | I11: =if(N(I7)>0,I7/12,) -> 6903.9148 | J11: =if(N(J7)>0,J7/12,) -> 7097.9951 | K11: =if(N(K7)>0,K7/12,) -> 7296.9275 | ... AV11: =if(N(AV7)>0,AV7/12,)
A12: Annual ISAs draw-down | D12: =IF(OR(D5=1,D5=2), Income!$F$14+Income!$F$15,) | E12: =IF(OR(E5=1,E5=2), Income!$F$14+Income!$F$15,) | F12: =IF(OR(F5=1,F5=2), Income!$F$14+Income!$F$15,) | G12: =IF(OR(G5=1,G5=2), Income!$F$14+Income!$F$15,) -> 8699.1 | H12: =IF(OR(H5=1,H5=2), Income!$F$14+Income!$F$15,) -> 8699.1 | I12: =IF(OR(I5=1,I5=2), Income!$F$14+Income!$F$15,) -> 8699.1 | J12: =IF(OR(J5=1,J5=2), Income!$F$14+Income!$F$15,) -> 8699.1 | K12: =IF(OR(K5=1,K5=2), Income!$F$14+Income!$F$15,) -> 8699.1 | ... AV12: =IF(OR(AV5=1,AV5=2), Income!$F$14+Income!$F$15,)
A13: Monthly ISA draw-down | D13: =if(D12>0,D12/12,) | E13: =if(E12>0,E12/12,) | F13: =if(F12>0,F12/12,) | G13: =if(G12>0,G12/12,) -> 724.925 | H13: =if(H12>0,H12/12,) -> 724.925 | I13: =if(I12>0,I12/12,) -> 724.925 | J13: =if(J12>0,J12/12,) -> 724.925 | K13: =if(K12>0,K12/12,) -> 724.925 | ... AV13: =if(AV12>0,AV12/12,)
A14: Annual Rent | D14: =if(D5=0,, if(D5=1,Income!$D$18, if(D5=2,C14*(1+Income!$E$18), if(D5=3,,)))) | E14: =if(E5=0,, if(E5=1,Income!$D$18, if(E5=2,D14*(1+Income!$E$18), if(E5=3,,)))) | F14: =if(F5=0,, if(F5=1,Income!$D$18, if(F5=2,E14*(1+Income!$E$18), if(F5=3,,)))) | G14: =if(G5=0,, if(G5=1,Income!$D$18, if(G5=2,F14*(1+Income!$E$18), if(G5=3,,)))) -> 20000 | H14: =if(H5=0,, if(H5=1,Income!$D$18, if(H5=2,G14*(1+Income!$E$18), if(H5=3,,)))) -> 20500 | I14: =if(I5=0,, if(I5=1,Income!$D$18, if(I5=2,H14*(1+Income!$E$18), if(I5=3,,)))) -> 21012.5 | J14: =if(J5=0,, if(J5=1,Income!$D$18, if(J5=2,I14*(1+Income!$E$18), if(J5=3,,)))) -> 21537.812 | K14: =if(K5=0,, if(K5=1,Income!$D$18, if(K5=2,J14*(1+Income!$E$18), if(K5=3,,)))) -> 22076.258 | ... AV14: =if(AV5=0,, if(AV5=1,Income!$D$18, if(AV5=2,AU14*(1+Income!$E$18), if(AV5=3,,))))
A15: Monthly Rent | D15: =if(D14>0,D14/12,) | E15: =if(E14>0,E14/12,) | F15: =if(F14>0,F14/12,) | G15: =if(G14>0,G14/12,) -> 1666.6667 | H15: =if(H14>0,H14/12,) -> 1708.3333 | I15: =if(I14>0,I14/12,) -> 1751.0417 | J15: =if(J14>0,J14/12,) -> 1794.8177 | K15: =if(K14>0,K14/12,) -> 1839.6882 | ... AV15: =if(AV14>0,AV14/12,)
A16: Annual State Pension | P16: =Income!$D$21 -> 17722.965 | Q16: =IF(Q5<3,P16*(1+'Person 1 Calculator'!$F$19),) -> 18431.883 | R16: =IF(R5<3,Q16*(1+'Person 1 Calculator'!$F$19),) -> 19169.159 | S16: =IF(S5<3,R16*(1+'Person 1 Calculator'!$F$19),) -> 19935.925 | T16: =IF(T5<3,S16*(1+'Person 1 Calculator'!$F$19),) -> 20733.362 | U16: =IF(U5<3,T16*(1+'Person 1 Calculator'!$F$19),) -> 21562.697 | V16: =IF(V5<3,U16*(1+'Person 1 Calculator'!$F$19),) -> 22425.204 | W16: =IF(W5<3,V16*(1+'Person 1 Calculator'!$F$19),) -> 23322.213 | X16: =IF(X5<3,W16*(1+'Person 1 Calculator'!$F$19),) -> 24255.101 | ... AV16: =IF(AV5<3,AU16*(1+'Person 1 Calculator'!$F$19),)
A17: Monthly State Pension | P17: =if(P16>0,P16/12,) -> 1476.9137 | Q17: =if(Q16>0,Q16/12,) -> 1535.9903 | R17: =if(R16>0,R16/12,) -> 1597.4299 | S17: =if(S16>0,S16/12,) -> 1661.3271 | T17: =if(T16>0,T16/12,) -> 1727.7802 | U17: =if(U16>0,U16/12,) -> 1796.8914 | V17: =if(V16>0,V16/12,) -> 1868.767 | W17: =if(W16>0,W16/12,) -> 1943.5177 | ... AV17: =if(AV16>0,AV16/12,)
A18: Annual Annuities | D18: =IFERROR(__xludf.DUMMYFUNCTION("IF( OR(D5=1, D5=2), SUM( FILTER( Income!$D$6:$D$8, D4 >= Income!$F$6:$F$8 ) ) ,)"),"") | E18: =IFERROR(__xludf.DUMMYFUNCTION("IF( OR(E5=1, E5=2), SUM( FILTER( Income!$D$6:$D$8, E4 >= Income!$F$6:$F$8 ) ) ,)"),"") | F18: =IFERROR(__xludf.DUMMYFUNCTION("IF( OR(F5=1, F5=2), SUM( FILTER( Income!$D$6:$D$8, F4 >= Income!$F$6:$F$8 ) ) ,)"),"") | G18: =IFERROR(__xludf.DUMMYFUNCTION("IF( OR(G5=1, G5=2), SUM( FILTER( Income!$D$6:$D$8, G4 >= Income!$F$6:$F$8 ) ) ,)"),0.0) -> 0 | H18: =IFERROR(__xludf.DUMMYFUNCTION("IF( OR(H5=1, H5=2), SUM( FILTER( Income!$D$6:$D$8, H4 >= Income!$F$6:$F$8 ) ) ,)"),0.0) -> 0 | I18: =IFERROR(__xludf.DUMMYFUNCTION("IF( OR(I5=1, I5=2), SUM( FILTER( Income!$D$6:$D$8, I4 >= Income!$F$6:$F$8 ) ) ,)"),0.0) -> 0 | J18: =IFERROR(__xludf.DUMMYFUNCTION("IF( OR(J5=1, J5=2), SUM( FILTER( Income!$D$6:$D$8, J4 >= Income!$F$6:$F$8 ) ) ,)"),0.0) -> 0 | K18: =IFERROR(__xludf.DUMMYFUNCTION("IF( OR(K5=1, K5=2), SUM( FILTER( Income!$D$6:$D$8, K4 >= Income!$F$6:$F$8 ) ) ,)"),0.0) -> 0 | L18: =IFERROR(__xludf.DUMMYFUNCTION("IF( OR(L5=1, L5=2), SUM( FILTER( Income!$D$6:$D$8, L4 >= Income!$F$6:$F$8 ) ) ,)"),0.0) -> 0 | M18: =IFERROR(__xludf.DUMMYFUNCTION("IF( OR(M5=1, M5=2), SUM( FILTER( Income!$D$6:$D$8, M4 >= Income!$F$6:$F$8 ) ) ,)"),0.0) -> 0 | N18: =IFERROR(__xludf.DUMMYFUNCTION("IF( OR(N5=1, N5=2), SUM( FILTER( Income!$D$6:$D$8, N4 >= Income!$F$6:$F$8 ) ) ,)"),0.0) -> 0 | O18: =IFERROR(__xludf.DUMMYFUNCTION("IF( OR(O5=1, O5=2), SUM( FILTER( Income!$D$6:$D$8, O4 >= Income!$F$6:$F$8 ) ) ,)"),0.0) -> 0 | P18: =IFERROR(__xludf.DUMMYFUNCTION("IF( OR(P5=1, P5=2), SUM( FILTER( Income!$D$6:$D$8, P4 >= Income!$F$6:$F$8 ) ) ,)"),0.0) -> 0 | Q18: =IFERROR(__xludf.DUMMYFUNCTION("IF( OR(Q5=1, Q5=2), SUM( FILTER( Income!$D$6:$D$8, Q4 >= Income!$F$6:$F$8 ) ) ,)"),0.0) -> 0 | R18: =IFERROR(__xludf.DUMMYFUNCTION("IF( OR(R5=1, R5=2), SUM( FILTER( Income!$D$6:$D$8, R4 >= Income!$F$6:$F$8 ) ) ,)"),0.0) -> 0 | S18: =IFERROR(__xludf.DUMMYFUNCTION("IF( OR(S5=1, S5=2), SUM( FILTER( Income!$D$6:$D$8, S4 >= Income!$F$6:$F$8 ) ) ,)"),0.0) -> 0 | T18: =IFERROR(__xludf.DUMMYFUNCTION("IF( OR(T5=1, T5=2), SUM( FILTER( Income!$D$6:$D$8, T4 >= Income!$F$6:$F$8 ) ) ,)"),0.0) -> 0 | U18: =IFERROR(__xludf.DUMMYFUNCTION("IF( OR(U5=1, U5=2), SUM( FILTER( Income!$D$6:$D$8, U4 >= Income!$F$6:$F$8 ) ) ,)"),0.0) -> 0 | V18: =IFERROR(__xludf.DUMMYFUNCTION("IF( OR(V5=1, V5=2), SUM( FILTER( Income!$D$6:$D$8, V4 >= Income!$F$6:$F$8 ) ) ,)"),0.0) -> 0 | W18: =IFERROR(__xludf.DUMMYFUNCTION("IF( OR(W5=1, W5=2), SUM( FILTER( Income!$D$6:$D$8, W4 >= Income!$F$6:$F$8 ) ) ,)"),0.0) -> 0 | X18: =IFERROR(__xludf.DUMMYFUNCTION("IF( OR(X5=1, X5=2), SUM( FILTER( Income!$D$6:$D$8, X4 >= Income!$F$6:$F$8 ) ) ,)"),0.0) -> 0 | Y18: =IFERROR(__xludf.DUMMYFUNCTION("IF( OR(Y5=1, Y5=2), SUM( FILTER( Income!$D$6:$D$8, Y4 >= Income!$F$6:$F$8 ) ) ,)"),0.0) -> 0 | Z18: =IFERROR(__xludf.DUMMYFUNCTION("IF( OR(Z5=1, Z5=2), SUM( FILTER( Income!$D$6:$D$8, Z4 >= Income!$F$6:$F$8 ) ) ,)"),0.0) -> 0 | AA18: =IFERROR(__xludf.DUMMYFUNCTION("IF( OR(AA5=1, AA5=2), SUM( FILTER( Income!$D$6:$D$8, AA4 >= Income!$F$6:$F$8 ) ) ,)"),0.0) -> 0 | AB18: =IFERROR(__xludf.DUMMYFUNCTION("IF( OR(AB5=1, AB5=2), SUM( FILTER( Income!$D$6:$D$8, AB4 >= Income!$F$6:$F$8 ) ) ,)"),0.0) -> 0 | AC18: =IFERROR(__xludf.DUMMYFUNCTION("IF( OR(AC5=1, AC5=2), SUM( FILTER( Income!$D$6:$D$8, AC4 >= Income!$F$6:$F$8 ) ) ,)"),0.0) -> 0 | AD18: =IFERROR(__xludf.DUMMYFUNCTION("IF( OR(AD5=1, AD5=2), SUM( FILTER( Income!$D$6:$D$8, AD4 >= Income!$F$6:$F$8 ) ) ,)"),0.0) -> 0 | AE18: =IFERROR(__xludf.DUMMYFUNCTION("IF( OR(AE5=1, AE5=2), SUM( FILTER( Income!$D$6:$D$8, AE4 >= Income!$F$6:$F$8 ) ) ,)"),0.0) -> 0 | AF18: =IFERROR(__xludf.DUMMYFUNCTION("IF( OR(AF5=1, AF5=2), SUM( FILTER( Income!$D$6:$D$8, AF4 >= Income!$F$6:$F$8 ) ) ,)"),0.0) -> 0 | AG18: =IFERROR(__xludf.DUMMYFUNCTION("IF( OR(AG5=1, AG5=2), SUM( FILTER( Income!$D$6:$D$8, AG4 >= Income!$F$6:$F$8 ) ) ,)"),0.0) -> 0 | AH18: =IFERROR(__xludf.DUMMYFUNCTION("IF( OR(AH5=1, AH5=2), SUM( FILTER( Income!$D$6:$D$8, AH4 >= Income!$F$6:$F$8 ) ) ,)"),0.0) -> 0 | AI18: =IFERROR(__xludf.DUMMYFUNCTION("IF( OR(AI5=1, AI5=2), SUM( FILTER( Income!$D$6:$D$8, AI4 >= Income!$F$6:$F$8 ) ) ,)"),0.0) -> 0 | AJ18: =IFERROR(__xludf.DUMMYFUNCTION("IF( OR(AJ5=1, AJ5=2), SUM( FILTER( Income!$D$6:$D$8, AJ4 >= Income!$F$6:$F$8 ) ) ,)"),0.0) -> 0 | AK18: =IFERROR(__xludf.DUMMYFUNCTION("IF( OR(AK5=1, AK5=2), SUM( FILTER( Income!$D$6:$D$8, AK4 >= Income!$F$6:$F$8 ) ) ,)"),0.0) -> 0 | AL18: =IFERROR(__xludf.DUMMYFUNCTION("IF( OR(AL5=1, AL5=2), SUM( FILTER( Income!$D$6:$D$8, AL4 >= Income!$F$6:$F$8 ) ) ,)"),0.0) -> 0 | AM18: =IFERROR(__xludf.DUMMYFUNCTION("IF( OR(AM5=1, AM5=2), SUM( FILTER( Income!$D$6:$D$8, AM4 >= Income!$F$6:$F$8 ) ) ,)"),"") | AN18: =IFERROR(__xludf.DUMMYFUNCTION("IF( OR(AN5=1, AN5=2), SUM( FILTER( Income!$D$6:$D$8, AN4 >= Income!$F$6:$F$8 ) ) ,)"),"") | AO18: =IFERROR(__xludf.DUMMYFUNCTION("IF( OR(AO5=1, AO5=2), SUM( FILTER( Income!$D$6:$D$8, AO4 >= Income!$F$6:$F$8 ) ) ,)"),"") | AP18: =IFERROR(__xludf.DUMMYFUNCTION("IF( OR(AP5=1, AP5=2), SUM( FILTER( Income!$D$6:$D$8, AP4 >= Income!$F$6:$F$8 ) ) ,)"),"") | AQ18: =IFERROR(__xludf.DUMMYFUNCTION("IF( OR(AQ5=1, AQ5=2), SUM( FILTER( Income!$D$6:$D$8, AQ4 >= Income!$F$6:$F$8 ) ) ,)"),"") | AR18: =IFERROR(__xludf.DUMMYFUNCTION("IF( OR(AR5=1, AR5=2), SUM( FILTER( Income!$D$6:$D$8, AR4 >= Income!$F$6:$F$8 ) ) ,)"),"") | AS18: =IFERROR(__xludf.DUMMYFUNCTION("IF( OR(AS5=1, AS5=2), SUM( FILTER( Income!$D$6:$D$8, AS4 >= Income!$F$6:$F$8 ) ) ,)"),"") | AT18: =IFERROR(__xludf.DUMMYFUNCTION("IF( OR(AT5=1, AT5=2), SUM( FILTER( Income!$D$6:$D$8, AT4 >= Income!$F$6:$F$8 ) ) ,)"),"") | AU18: =IFERROR(__xludf.DUMMYFUNCTION("IF( OR(AU5=1, AU5=2), SUM( FILTER( Income!$D$6:$D$8, AU4 >= Income!$F$6:$F$8 ) ) ,)"),"") | AV18: =IFERROR(__xludf.DUMMYFUNCTION("IF( OR(AV5=1, AV5=2), SUM( FILTER( Income!$D$6:$D$8, AV4 >= Income!$F$6:$F$8 ) ) ,)"),"")
A19: Monthly Annuity | D19: =if(D18>0,D18/12,) | E19: =if(E18>0,E18/12,) | F19: =if(F18>0,F18/12,) | G19: =if(G18>0,G18/12,) | H19: =if(H18>0,H18/12,) | I19: =if(I18>0,I18/12,) | J19: =if(J18>0,J18/12,) | K19: =if(K18>0,K18/12,) | ... AV19: =if(AV18>0,AV18/12,)
A20: Annual DB Pensions | D20: =IFERROR(__xludf.DUMMYFUNCTION("IF( OR(D5=1, D5=2), SUM( FILTER( Income!$D$10:$D$12, D4 >= Income!$F$10:$F$12 ) ) ,)"),"") | E20: =IFERROR(__xludf.DUMMYFUNCTION("IF( OR(E5=1, E5=2), SUM( FILTER( Income!$D$10:$D$12, E4 >= Income!$F$10:$F$12 ) ) ,)"),"") | F20: =IFERROR(__xludf.DUMMYFUNCTION("IF( OR(F5=1, F5=2), SUM( FILTER( Income!$D$10:$D$12, F4 >= Income!$F$10:$F$12 ) ) ,)"),"") | G20: =IFERROR(__xludf.DUMMYFUNCTION("IF( OR(G5=1, G5=2), SUM( FILTER( Income!$D$10:$D$12, G4 >= Income!$F$10:$F$12 ) ) ,)"),0.0) -> 0 | H20: =IFERROR(__xludf.DUMMYFUNCTION("IF( OR(H5=1, H5=2), SUM( FILTER( Income!$D$10:$D$12, H4 >= Income!$F$10:$F$12 ) ) ,)"),0.0) -> 0 | I20: =IFERROR(__xludf.DUMMYFUNCTION("IF( OR(I5=1, I5=2), SUM( FILTER( Income!$D$10:$D$12, I4 >= Income!$F$10:$F$12 ) ) ,)"),0.0) -> 0 | J20: =IFERROR(__xludf.DUMMYFUNCTION("IF( OR(J5=1, J5=2), SUM( FILTER( Income!$D$10:$D$12, J4 >= Income!$F$10:$F$12 ) ) ,)"),0.0) -> 0 | K20: =IFERROR(__xludf.DUMMYFUNCTION("IF( OR(K5=1, K5=2), SUM( FILTER( Income!$D$10:$D$12, K4 >= Income!$F$10:$F$12 ) ) ,)"),0.0) -> 0 | L20: =IFERROR(__xludf.DUMMYFUNCTION("IF( OR(L5=1, L5=2), SUM( FILTER( Income!$D$10:$D$12, L4 >= Income!$F$10:$F$12 ) ) ,)"),0.0) -> 0 | M20: =IFERROR(__xludf.DUMMYFUNCTION("IF( OR(M5=1, M5=2), SUM( FILTER( Income!$D$10:$D$12, M4 >= Income!$F$10:$F$12 ) ) ,)"),0.0) -> 0 | N20: =IFERROR(__xludf.DUMMYFUNCTION("IF( OR(N5=1, N5=2), SUM( FILTER( Income!$D$10:$D$12, N4 >= Income!$F$10:$F$12 ) ) ,)"),0.0) -> 0 | O20: =IFERROR(__xludf.DUMMYFUNCTION("IF( OR(O5=1, O5=2), SUM( FILTER( Income!$D$10:$D$12, O4 >= Income!$F$10:$F$12 ) ) ,)"),0.0) -> 0 | P20: =IFERROR(__xludf.DUMMYFUNCTION("IF( OR(P5=1, P5=2), SUM( FILTER( Income!$D$10:$D$12, P4 >= Income!$F$10:$F$12 ) ) ,)"),0.0) -> 0 | Q20: =IFERROR(__xludf.DUMMYFUNCTION("IF( OR(Q5=1, Q5=2), SUM( FILTER( Income!$D$10:$D$12, Q4 >= Income!$F$10:$F$12 ) ) ,)"),0.0) -> 0 | R20: =IFERROR(__xludf.DUMMYFUNCTION("IF( OR(R5=1, R5=2), SUM( FILTER( Income!$D$10:$D$12, R4 >= Income!$F$10:$F$12 ) ) ,)"),0.0) -> 0 | S20: =IFERROR(__xludf.DUMMYFUNCTION("IF( OR(S5=1, S5=2), SUM( FILTER( Income!$D$10:$D$12, S4 >= Income!$F$10:$F$12 ) ) ,)"),0.0) -> 0 | T20: =IFERROR(__xludf.DUMMYFUNCTION("IF( OR(T5=1, T5=2), SUM( FILTER( Income!$D$10:$D$12, T4 >= Income!$F$10:$F$12 ) ) ,)"),0.0) -> 0 | U20: =IFERROR(__xludf.DUMMYFUNCTION("IF( OR(U5=1, U5=2), SUM( FILTER( Income!$D$10:$D$12, U4 >= Income!$F$10:$F$12 ) ) ,)"),0.0) -> 0 | V20: =IFERROR(__xludf.DUMMYFUNCTION("IF( OR(V5=1, V5=2), SUM( FILTER( Income!$D$10:$D$12, V4 >= Income!$F$10:$F$12 ) ) ,)"),0.0) -> 0 | W20: =IFERROR(__xludf.DUMMYFUNCTION("IF( OR(W5=1, W5=2), SUM( FILTER( Income!$D$10:$D$12, W4 >= Income!$F$10:$F$12 ) ) ,)"),0.0) -> 0 | X20: =IFERROR(__xludf.DUMMYFUNCTION("IF( OR(X5=1, X5=2), SUM( FILTER( Income!$D$10:$D$12, X4 >= Income!$F$10:$F$12 ) ) ,)"),0.0) -> 0 | Y20: =IFERROR(__xludf.DUMMYFUNCTION("IF( OR(Y5=1, Y5=2), SUM( FILTER( Income!$D$10:$D$12, Y4 >= Income!$F$10:$F$12 ) ) ,)"),0.0) -> 0 | Z20: =IFERROR(__xludf.DUMMYFUNCTION("IF( OR(Z5=1, Z5=2), SUM( FILTER( Income!$D$10:$D$12, Z4 >= Income!$F$10:$F$12 ) ) ,)"),0.0) -> 0 | AA20: =IFERROR(__xludf.DUMMYFUNCTION("IF( OR(AA5=1, AA5=2), SUM( FILTER( Income!$D$10:$D$12, AA4 >= Income!$F$10:$F$12 ) ) ,)"),0.0) -> 0 | AB20: =IFERROR(__xludf.DUMMYFUNCTION("IF( OR(AB5=1, AB5=2), SUM( FILTER( Income!$D$10:$D$12, AB4 >= Income!$F$10:$F$12 ) ) ,)"),0.0) -> 0 | AC20: =IFERROR(__xludf.DUMMYFUNCTION("IF( OR(AC5=1, AC5=2), SUM( FILTER( Income!$D$10:$D$12, AC4 >= Income!$F$10:$F$12 ) ) ,)"),0.0) -> 0 | AD20: =IFERROR(__xludf.DUMMYFUNCTION("IF( OR(AD5=1, AD5=2), SUM( FILTER( Income!$D$10:$D$12, AD4 >= Income!$F$10:$F$12 ) ) ,)"),0.0) -> 0 | AE20: =IFERROR(__xludf.DUMMYFUNCTION("IF( OR(AE5=1, AE5=2), SUM( FILTER( Income!$D$10:$D$12, AE4 >= Income!$F$10:$F$12 ) ) ,)"),0.0) -> 0 | AF20: =IFERROR(__xludf.DUMMYFUNCTION("IF( OR(AF5=1, AF5=2), SUM( FILTER( Income!$D$10:$D$12, AF4 >= Income!$F$10:$F$12 ) ) ,)"),0.0) -> 0 | AG20: =IFERROR(__xludf.DUMMYFUNCTION("IF( OR(AG5=1, AG5=2), SUM( FILTER( Income!$D$10:$D$12, AG4 >= Income!$F$10:$F$12 ) ) ,)"),0.0) -> 0 | AH20: =IFERROR(__xludf.DUMMYFUNCTION("IF( OR(AH5=1, AH5=2), SUM( FILTER( Income!$D$10:$D$12, AH4 >= Income!$F$10:$F$12 ) ) ,)"),0.0) -> 0 | AI20: =IFERROR(__xludf.DUMMYFUNCTION("IF( OR(AI5=1, AI5=2), SUM( FILTER( Income!$D$10:$D$12, AI4 >= Income!$F$10:$F$12 ) ) ,)"),0.0) -> 0 | AJ20: =IFERROR(__xludf.DUMMYFUNCTION("IF( OR(AJ5=1, AJ5=2), SUM( FILTER( Income!$D$10:$D$12, AJ4 >= Income!$F$10:$F$12 ) ) ,)"),0.0) -> 0 | AK20: =IFERROR(__xludf.DUMMYFUNCTION("IF( OR(AK5=1, AK5=2), SUM( FILTER( Income!$D$10:$D$12, AK4 >= Income!$F$10:$F$12 ) ) ,)"),0.0) -> 0 | AL20: =IFERROR(__xludf.DUMMYFUNCTION("IF( OR(AL5=1, AL5=2), SUM( FILTER( Income!$D$10:$D$12, AL4 >= Income!$F$10:$F$12 ) ) ,)"),0.0) -> 0 | AM20: =IFERROR(__xludf.DUMMYFUNCTION("IF( OR(AM5=1, AM5=2), SUM( FILTER( Income!$D$10:$D$12, AM4 >= Income!$F$10:$F$12 ) ) ,)"),"") | AN20: =IFERROR(__xludf.DUMMYFUNCTION("IF( OR(AN5=1, AN5=2), SUM( FILTER( Income!$D$10:$D$12, AN4 >= Income!$F$10:$F$12 ) ) ,)"),"") | AO20: =IFERROR(__xludf.DUMMYFUNCTION("IF( OR(AO5=1, AO5=2), SUM( FILTER( Income!$D$10:$D$12, AO4 >= Income!$F$10:$F$12 ) ) ,)"),"") | AP20: =IFERROR(__xludf.DUMMYFUNCTION("IF( OR(AP5=1, AP5=2), SUM( FILTER( Income!$D$10:$D$12, AP4 >= Income!$F$10:$F$12 ) ) ,)"),"") | AQ20: =IFERROR(__xludf.DUMMYFUNCTION("IF( OR(AQ5=1, AQ5=2), SUM( FILTER( Income!$D$10:$D$12, AQ4 >= Income!$F$10:$F$12 ) ) ,)"),"") | AR20: =IFERROR(__xludf.DUMMYFUNCTION("IF( OR(AR5=1, AR5=2), SUM( FILTER( Income!$D$10:$D$12, AR4 >= Income!$F$10:$F$12 ) ) ,)"),"") | AS20: =IFERROR(__xludf.DUMMYFUNCTION("IF( OR(AS5=1, AS5=2), SUM( FILTER( Income!$D$10:$D$12, AS4 >= Income!$F$10:$F$12 ) ) ,)"),"") | AT20: =IFERROR(__xludf.DUMMYFUNCTION("IF( OR(AT5=1, AT5=2), SUM( FILTER( Income!$D$10:$D$12, AT4 >= Income!$F$10:$F$12 ) ) ,)"),"") | AU20: =IFERROR(__xludf.DUMMYFUNCTION("IF( OR(AU5=1, AU5=2), SUM( FILTER( Income!$D$10:$D$12, AU4 >= Income!$F$10:$F$12 ) ) ,)"),"") | AV20: =IFERROR(__xludf.DUMMYFUNCTION("IF( OR(AV5=1, AV5=2), SUM( FILTER( Income!$D$10:$D$12, AV4 >= Income!$F$10:$F$12 ) ) ,)"),"")
A21: Monthly DB Pension | D21: =if(D20>0,D20/12,) | E21: =if(E20>0,E20/12,) | F21: =if(F20>0,F20/12,) | G21: =if(G20>0,G20/12,) | H21: =if(H20>0,H20/12,) | I21: =if(I20>0,I20/12,) | J21: =if(J20>0,J20/12,) | K21: =if(K20>0,K20/12,) | ... AV21: =if(AV20>0,AV20/12,)
A22: Annual Cash | D22: =IF( OR(D5=1, D5=2),Income!$F$16 ,) | E22: =IF( OR(E5=1, E5=2),Income!$F$16 ,) | F22: =IF( OR(F5=1, F5=2),Income!$F$16 ,) | G22: =IF( OR(G5=1, G5=2),Income!$F$16 ,) -> 1612.5 | H22: =IF( OR(H5=1, H5=2),Income!$F$16 ,) -> 1612.5 | I22: =IF( OR(I5=1, I5=2),Income!$F$16 ,) -> 1612.5 | J22: =IF( OR(J5=1, J5=2),Income!$F$16 ,) -> 1612.5 | K22: =IF( OR(K5=1, K5=2),Income!$F$16 ,) -> 1612.5 | ... AV22: =IF( OR(AV5=1, AV5=2),Income!$F$16 ,)
A23: Monthly Cash | D23: =if(D22>0, D22 / 12,) | E23: =if(E22>0, E22 / 12,) | F23: =if(F22>0, F22 / 12,) | G23: =if(G22>0, G22 / 12,) -> 134.375 | H23: =if(H22>0, H22 / 12,) -> 134.375 | I23: =if(I22>0, I22 / 12,) -> 134.375 | J23: =if(J22>0, J22 / 12,) -> 134.375 | K23: =if(K22>0, K22 / 12,) -> 134.375 | ... AV23: =if(AV22>0, AV22 / 12,)
A24: Total Annual Income | D24: =IF( D5=0,, if( D5=1, 'Person 1 Calculator'!$F$9, if(D5=2, D7+D12+D14+D16+D18+D20+D22,if(D5=3,) ))) | E24: =IF( E5=0,, if( E5=1, 'Person 1 Calculator'!$F$9, if(E5=2, E7+E12+E14+E16+E18+E20+E22,if(E5=3,) ))) | F24: =IF( F5=0,, if( F5=1, 'Person 1 Calculator'!$F$9, if(F5=2, F7+F12+F14+F16+F18+F20+F22,if(F5=3,) ))) | G24: =IF( G5=0,, if( G5=1, 'Person 1 Calculator'!$F$9, if(G5=2, G7+G12+G14+G16+G18+G20+G22,if(G5=3,) ))) -> 108669.67 | H24: =IF( H5=0,, if( H5=1, 'Person 1 Calculator'!$F$9, if(H5=2, H7+H12+H14+H16+H18+H20+H22,if(H5=3,) ))) -> 111386.42 | I24: =IF( I5=0,, if( I5=1, 'Person 1 Calculator'!$F$9, if(I5=2, I7+I12+I14+I16+I18+I20+I22,if(I5=3,) ))) -> 114171.08 | J24: =IF( J5=0,, if( J5=1, 'Person 1 Calculator'!$F$9, if(J5=2, J7+J12+J14+J16+J18+J20+J22,if(J5=3,) ))) -> 117025.35 | K24: =IF( K5=0,, if( K5=1, 'Person 1 Calculator'!$F$9, if(K5=2, K7+K12+K14+K16+K18+K20+K22,if(K5=3,) ))) -> 119950.99 | ... AV24: =IF( AV5=0,, if( AV5=1, 'Person 1 Calculator'!$F$9, if(AV5=2, AV7+AV12+AV14+AV16+AV18+AV20+AV22,if(AV5=3,) )))
A25: Total Monthly Income | D25: =if(D24>0,D24/12,) | E25: =if(E24>0,E24/12,) | F25: =if(F24>0,F24/12,) | G25: =if(G24>0,G24/12,) -> 9055.8062 | H25: =if(H24>0,H24/12,) -> 9282.2014 | I25: =if(I24>0,I24/12,) -> 9514.2564 | J25: =if(J24>0,J24/12,) -> 9752.1128 | K25: =if(K24>0,K24/12,) -> 9995.9157 | ... AV25: =if(AV24>0,AV24/12,)
A26: =concatenate("Target income with inflation of ",text('Person 1 Calculator'!F18,"0.0%")) -> Target income with inflation of 2.5% | D26: =if(D5=0,, if( D5=1, D24,if(D5=2,C26*(1+'Person 1 Calculator'!$F$18),if(D5=3,)))) | E26: =if(E5=0,, if( E5=1, E24,if(E5=2,D26*(1+'Person 1 Calculator'!$F$18),if(E5=3,)))) | F26: =if(F5=0,, if( F5=1, F24,if(F5=2,E26*(1+'Person 1 Calculator'!$F$18),if(F5=3,)))) | G26: =if(G5=0,, if( G5=1, G24,if(G5=2,F26*(1+'Person 1 Calculator'!$F$18),if(G5=3,)))) -> 108669.67 | H26: =if(H5=0,, if( H5=1, H24,if(H5=2,G26*(1+'Person 1 Calculator'!$F$18),if(H5=3,)))) -> 111386.42 | I26: =if(I5=0,, if( I5=1, I24,if(I5=2,H26*(1+'Person 1 Calculator'!$F$18),if(I5=3,)))) -> 114171.08 | J26: =if(J5=0,, if( J5=1, J24,if(J5=2,I26*(1+'Person 1 Calculator'!$F$18),if(J5=3,)))) -> 117025.35 | K26: =if(K5=0,, if( K5=1, K24,if(K5=2,J26*(1+'Person 1 Calculator'!$F$18),if(K5=3,)))) -> 119950.99 | ... AV26: =if(AV5=0,, if( AV5=1, AV24,if(AV5=2,AU26*(1+'Person 1 Calculator'!$F$18),if(AV5=3,))))
A27: Performance against inflation | D27: =if(AND(D24>0, D26>0),D24/D26,) | E27: =if(AND(E24>0, E26>0),E24/E26,) | F27: =if(AND(F24>0, F26>0),F24/F26,) | G27: =if(AND(G24>0, G26>0),G24/G26,) -> 1 | H27: =if(AND(H24>0, H26>0),H24/H26,) -> 1 | I27: =if(AND(I24>0, I26>0),I24/I26,) -> 1 | J27: =if(AND(J24>0, J26>0),J24/J26,) -> 1 | K27: =if(AND(K24>0, K26>0),K24/K26,) -> 1 | ... AV27: =if(AND(AV24>0, AV26>0),AV24/AV26,)
A28: Annual SIPP Draw-down Rate | D28: =if(D6>D7,D7/D6,) | E28: =if(E6>E7,E7/E6,) | F28: =if(F6>F7,F7/F6,) | G28: =if(G6>G7,G7/G6,) -> 0.079356856 | H28: =if(H6>H7,H7/H6,) -> 0.082979467 | I28: =if(I6>I7,I7/I6,) -> 0.087089037 | J28: =if(J6>J7,J7/J6,) -> 0.091789515 | K28: =if(K6>K7,K7/K6,) -> 0.097216537 | ... AV28: =if(AV6>AV7,AV7/AV6,)
A29: Taxable income | D29: =if(D24=0,,(if(AND(D24>0,D10<268275), D8+D14+D16+D18+D20+D22,if(D10>268275,D8+D9+D14+D16+D18+D20+D22)))) | E29: =if(E24=0,,(if(AND(E24>0,E10<268275), E8+E14+E16+E18+E20+E22,if(E10>268275,E8+E9+E14+E16+E18+E20+E22)))) | F29: =if(F24=0,,(if(AND(F24>0,F10<268275), F8+F14+F16+F18+F20+F22,if(F10>268275,F8+F9+F14+F16+F18+F20+F22)))) | G29: =if(G24=0,,(if(AND(G24>0,G10<268275), G8+G14+G16+G18+G20+G22,if(G10>268275,G8+G9+G14+G16+G18+G20+G22)))) -> 80381.056 | H29: =if(H24=0,,(if(AND(H24>0,H10<268275), H8+H14+H16+H18+H20+H22,if(H10>268275,H8+H9+H14+H16+H18+H20+H22)))) -> 82543.613 | I29: =if(I24=0,,(if(AND(I24>0,I10<268275), I8+I14+I16+I18+I20+I22,if(I10>268275,I8+I9+I14+I16+I18+I20+I22)))) -> 84760.233 | J29: =if(J24=0,,(if(AND(J24>0,J10<268275), J8+J14+J16+J18+J20+J22,if(J10>268275,J8+J9+J14+J16+J18+J20+J22)))) -> 87032.269 | K29: =if(K24=0,,(if(AND(K24>0,K10<268275), K8+K14+K16+K18+K20+K22,if(K10>268275,K8+K9+K14+K16+K18+K20+K22)))) -> 89361.105 | ... AV29: =if(AV24=0,,(if(AND(AV24>0,AV10<268275), AV8+AV14+AV16+AV18+AV20+AV22,if(AV10>268275,AV8+AV9+AV14+AV16+AV18+AV20+AV22))))
A30: Tax | D30: =LET( Income, D29, PA_Limit, 12570, BR_Limit, 50270, HR_Limit, 125140, Taper_Start, 100000, Tapered_PA, MAX(0, PA_Limit - MAX(0, (Income - Taper_Start) / 2)), TaxableIncome, MAX(0, Income - Tapered_PA), BasicRateTax, MAX(0, MIN(TaxableIncome, BR_Limit - PA_Limit)) * 0.2, HigherRateBandWidth, HR_Limit - BR_Limit, HigherRateTax, MAX(0, MIN(TaxableIncome - (BR_Limit - PA_Limit), HigherRateBandWidth)) * 0.4, AdditionalRateTax, MAX(0, TaxableIncome - (HR_Limit - PA_Limit)) * 0.45, TotalTax, BasicRateTax + HigherRateTax + AdditionalRateTax, IF(OR(ISBLANK(Income), Income = 0), "", TotalTax) ) | E30: =LET( Income, E29, PA_Limit, 12570, BR_Limit, 50270, HR_Limit, 125140, Taper_Start, 100000, Tapered_PA, MAX(0, PA_Limit - MAX(0, (Income - Taper_Start) / 2)), TaxableIncome, MAX(0, Income - Tapered_PA), BasicRateTax, MAX(0, MIN(TaxableIncome, BR_Limit - PA_Limit)) * 0.2, HigherRateBandWidth, HR_Limit - BR_Limit, HigherRateTax, MAX(0, MIN(TaxableIncome - (BR_Limit - PA_Limit), HigherRateBandWidth)) * 0.4, AdditionalRateTax, MAX(0, TaxableIncome - (HR_Limit - PA_Limit)) * 0.45, TotalTax, BasicRateTax + HigherRateTax + AdditionalRateTax, IF(OR(ISBLANK(Income), Income = 0), "", TotalTax) ) | F30: =LET( Income, F29, PA_Limit, 12570, BR_Limit, 50270, HR_Limit, 125140, Taper_Start, 100000, Tapered_PA, MAX(0, PA_Limit - MAX(0, (Income - Taper_Start) / 2)), TaxableIncome, MAX(0, Income - Tapered_PA), BasicRateTax, MAX(0, MIN(TaxableIncome, BR_Limit - PA_Limit)) * 0.2, HigherRateBandWidth, HR_Limit - BR_Limit, HigherRateTax, MAX(0, MIN(TaxableIncome - (BR_Limit - PA_Limit), HigherRateBandWidth)) * 0.4, AdditionalRateTax, MAX(0, TaxableIncome - (HR_Limit - PA_Limit)) * 0.45, TotalTax, BasicRateTax + HigherRateTax + AdditionalRateTax, IF(OR(ISBLANK(Income), Income = 0), "", TotalTax) ) | G30: =LET( Income, G29, PA_Limit, 12570, BR_Limit, 50270, HR_Limit, 125140, Taper_Start, 100000, Tapered_PA, MAX(0, PA_Limit - MAX(0, (Income - Taper_Start) / 2)), TaxableIncome, MAX(0, Income - Tapered_PA), BasicRateTax, MAX(0, MIN(TaxableIncome, BR_Limit - PA_Limit)) * 0.2, HigherRateBandWidth, HR_Limit - BR_Limit, HigherRateTax, MAX(0, MIN(TaxableIncome - (BR_Limit - PA_Limit), HigherRateBandWidth)) * 0.4, AdditionalRateTax, MAX(0, TaxableIncome - (HR_Limit - PA_Limit)) * 0.45, TotalTax, BasicRateTax + HigherRateTax + AdditionalRateTax, IF(OR(ISBLANK(Income), Income = 0), "", TotalTax) ) -> 19584.422 | H30: =LET( Income, H29, PA_Limit, 12570, BR_Limit, 50270, HR_Limit, 125140, Taper_Start, 100000, Tapered_PA, MAX(0, PA_Limit - MAX(0, (Income - Taper_Start) / 2)), TaxableIncome, MAX(0, Income - Tapered_PA), BasicRateTax, MAX(0, MIN(TaxableIncome, BR_Limit - PA_Limit)) * 0.2, HigherRateBandWidth, HR_Limit - BR_Limit, HigherRateTax, MAX(0, MIN(TaxableIncome - (BR_Limit - PA_Limit), HigherRateBandWidth)) * 0.4, AdditionalRateTax, MAX(0, TaxableIncome - (HR_Limit - PA_Limit)) * 0.45, TotalTax, BasicRateTax + HigherRateTax + AdditionalRateTax, IF(OR(ISBLANK(Income), Income = 0), "", TotalTax) ) -> 20449.445 | I30: =LET( Income, I29, PA_Limit, 12570, BR_Limit, 50270, HR_Limit, 125140, Taper_Start, 100000, Tapered_PA, MAX(0, PA_Limit - MAX(0, (Income - Taper_Start) / 2)), TaxableIncome, MAX(0, Income - Tapered_PA), BasicRateTax, MAX(0, MIN(TaxableIncome, BR_Limit - PA_Limit)) * 0.2, HigherRateBandWidth, HR_Limit - BR_Limit, HigherRateTax, MAX(0, MIN(TaxableIncome - (BR_Limit - PA_Limit), HigherRateBandWidth)) * 0.4, AdditionalRateTax, MAX(0, TaxableIncome - (HR_Limit - PA_Limit)) * 0.45, TotalTax, BasicRateTax + HigherRateTax + AdditionalRateTax, IF(OR(ISBLANK(Income), Income = 0), "", TotalTax) ) -> 21336.093 | J30: =LET( Income, J29, PA_Limit, 12570, BR_Limit, 50270, HR_Limit, 125140, Taper_Start, 100000, Tapered_PA, MAX(0, PA_Limit - MAX(0, (Income - Taper_Start) / 2)), TaxableIncome, MAX(0, Income - Tapered_PA), BasicRateTax, MAX(0, MIN(TaxableIncome, BR_Limit - PA_Limit)) * 0.2, HigherRateBandWidth, HR_Limit - BR_Limit, HigherRateTax, MAX(0, MIN(TaxableIncome - (BR_Limit - PA_Limit), HigherRateBandWidth)) * 0.4, AdditionalRateTax, MAX(0, TaxableIncome - (HR_Limit - PA_Limit)) * 0.45, TotalTax, BasicRateTax + HigherRateTax + AdditionalRateTax, IF(OR(ISBLANK(Income), Income = 0), "", TotalTax) ) -> 22244.907 | K30: =LET( Income, K29, PA_Limit, 12570, BR_Limit, 50270, HR_Limit, 125140, Taper_Start, 100000, Tapered_PA, MAX(0, PA_Limit - MAX(0, (Income - Taper_Start) / 2)), TaxableIncome, MAX(0, Income - Tapered_PA), BasicRateTax, MAX(0, MIN(TaxableIncome, BR_Limit - PA_Limit)) * 0.2, HigherRateBandWidth, HR_Limit - BR_Limit, HigherRateTax, MAX(0, MIN(TaxableIncome - (BR_Limit - PA_Limit), HigherRateBandWidth)) * 0.4, AdditionalRateTax, MAX(0, TaxableIncome - (HR_Limit - PA_Limit)) * 0.45, TotalTax, BasicRateTax + HigherRateTax + AdditionalRateTax, IF(OR(ISBLANK(Income), Income = 0), "", TotalTax) ) -> 23176.442 | ... AV30: =LET( Income, AV29, PA_Limit, 12570, BR_Limit, 50270, HR_Limit, 125140, Taper_Start, 100000, Tapered_PA, MAX(0, PA_Limit - MAX(0, (Income - Taper_Start) / 2)), TaxableIncome, MAX(0, Income - Tapered_PA), BasicRateTax, MAX(0, MIN(TaxableIncome, BR_Limit - PA_Limit)) * 0.2, HigherRateBandWidth, HR_Limit - BR_Limit, HigherRateTax, MAX(0, MIN(TaxableIncome - (BR_Limit - PA_Limit), HigherRateBandWidth)) * 0.4, AdditionalRateTax, MAX(0, TaxableIncome - (HR_Limit - PA_Limit)) * 0.45, TotalTax, BasicRateTax + HigherRateTax + AdditionalRateTax, IF(OR(ISBLANK(Income), Income = 0), "", TotalTax) )
A31: Effective tax rate | D31: =if(AND(D30>0, D24>0),D30/D24,) | E31: =if(AND(E30>0, E24>0),E30/E24,) | F31: =if(AND(F30>0, F24>0),F30/F24,) | G31: =if(AND(G30>0, G24>0),G30/G24,) -> 0.18021976 | H31: =if(AND(H30>0, H24>0),H30/H24,) -> 0.18359011 | I31: =if(AND(I30>0, I24>0),I30/I24,) -> 0.18687827 | J31: =if(AND(J30>0, J24>0),J30/J24,) -> 0.19008622 | K31: =if(AND(K30>0, K24>0),K30/K24,) -> 0.19321593 | ... AV31: =if(AND(AV30>0, AV24>0),AV30/AV24,)
A32: Total Net Income | D32: =if(D24>0,D24-D30,) | E32: =if(E24>0,E24-E30,) | F32: =if(F24>0,F24-F30,) | G32: =if(G24>0,G24-G30,) -> 89085.252 | H32: =if(H24>0,H24-H30,) -> 90936.972 | I32: =if(I24>0,I24-I30,) -> 92834.984 | J32: =if(J24>0,J24-J30,) -> 94780.447 | K32: =if(K24>0,K24-K30,) -> 96774.546 | ... AV32: =if(AV24>0,AV24-AV30,)
A33: Net Income Monthly | D33: =if(D32>0,D32/12,) | E33: =if(E32>0,E32/12,) | F33: =if(F32>0,F32/12,) | G33: =if(G32>0,G32/12,) -> 7423.771 | H33: =if(H32>0,H32/12,) -> 7578.081 | I33: =if(I32>0,I32/12,) -> 7736.2487 | J33: =if(J32>0,J32/12,) -> 7898.3706 | K33: =if(K32>0,K32/12,) -> 8064.5455 | ... AV33: =if(AV32>0,AV32/12,)
A34: NPV | D34: =if(OR(D5=1,D5=2),D27*'Person 1 Calculator'!$F$9,) | E34: =if(OR(E5=1,E5=2),E27*'Person 1 Calculator'!$F$9,) | F34: =if(OR(F5=1,F5=2),F27*'Person 1 Calculator'!$F$9,) | G34: =if(OR(G5=1,G5=2),G27*'Person 1 Calculator'!$F$9,) -> 108669.67 | H34: =if(OR(H5=1,H5=2),H27*'Person 1 Calculator'!$F$9,) -> 108669.67 | I34: =if(OR(I5=1,I5=2),I27*'Person 1 Calculator'!$F$9,) -> 108669.67 | J34: =if(OR(J5=1,J5=2),J27*'Person 1 Calculator'!$F$9,) -> 108669.67 | K34: =if(OR(K5=1,K5=2),K27*'Person 1 Calculator'!$F$9,) -> 108669.67 | ... AV34: =if(OR(AV5=1,AV5=2),AV27*'Person 1 Calculator'!$F$9,)
A35: Net NPV | D35: =if(OR(D5=1,D5=2),D27*'Person 1 Calculator'!$D$9,) | E35: =if(OR(E5=1,E5=2),E27*'Person 1 Calculator'!$D$9,) | F35: =if(OR(F5=1,F5=2),F27*'Person 1 Calculator'!$D$9,) | G35: =if(OR(G5=1,G5=2),G27*'Person 1 Calculator'!$D$9,) -> 89085.252 | H35: =if(OR(H5=1,H5=2),H27*'Person 1 Calculator'!$D$9,) -> 89085.252 | I35: =if(OR(I5=1,I5=2),I27*'Person 1 Calculator'!$D$9,) -> 89085.252 | J35: =if(OR(J5=1,J5=2),J27*'Person 1 Calculator'!$D$9,) -> 89085.252 | K35: =if(OR(K5=1,K5=2),K27*'Person 1 Calculator'!$D$9,) -> 89085.252 | ... AV35: =if(OR(AV5=1,AV5=2),AV27*'Person 1 Calculator'!$D$9,)

Sheet Person 2 Calculator
B1: Person 2 Pension Calculator
B2: Parameters | H2: Income Performance
B3: Year of Birth | F3: 1969
B4: Start Draw-down In | F4: 2026
B5: End Draw-down By | F5: 2058
B6: Private Pension Eligible Year (age 55) | F6: =F3+55 -> 2024
B7: State Pension Eligible Year | F7: =F3+67 -> 2036
B8: Final Year Percentage (keep hidden)
B9: First Year Estimated Income | C9: Net | D9: ='Person 2 Draw-down'!G32 -> 18924.1 | E9: | Gross | F9: 18924.1
B10: Estimated Income @ 70 | C10: Net Real | D10: ='Person 2 Draw-down'!S27*$D$9 -> 30366.115 | E10: | Nominal Gross | F10: ='Person 2 Draw-down'!S24 -> 41860.025 | I10: =Income!$K$4 -> 0
B11: Estimated Income @ 80 | C11: Net Real | D11: ='Person 2 Draw-down'!AC27*$D$9 -> 29147.585 | E11: | Nominal Gross | F11: ='Person 2 Draw-down'!AC24 -> 51434.139 | I11: =I10 -> 0
B12: Final Year Estimated Income | C12: Net Real | D12: ='Person 2 Draw-down'!AJ27*$D$9 -> 28965.598 | E12: | Nominal Gross | F12: ='Person 2 Draw-down'!AJ24 -> 60757.298
B13: Final Year SIPP Balance Target | F13: 0
B14: Final Year SIPP Balance | F14: ='Person 2 Draw-down'!AJ6
B16: Optional annual spending reduction from age 70 | F16: 0.2
B17: Optional annual spending reduction from age 80 | F17: 0.4
B18: Inflation | F18: 0.025
B19: State Pension Growth (triple-lock) | F19: 0.04
B20: Inflation tracking mode | F20: Smooth
A50: Age | B50: ISA | C50: Rent | D50: State Pension | E50: Annuities | F50: DB Pensions | G50: Cash | H50: Total Annual Income | I50: Inflation | J50: Tax | K50: Total Net Income
A51: 57 | B51: 7086.61 | C51: 0 | D51: 0 | E51: 0 | F51: 7000 | G51: 4837.49 | H51: 18924.1 | I51: 18924.1 | J51: 0 | K51: 18924.1
A52: 58 | B52: 7086.61 | C52: 0 | D52: 0 | E52: 0 | F52: 7000 | G52: 4837.49 | H52: 18924.1 | I52: 19397.202 | J52: 0 | K52: 18924.1
A53: 59 | B53: 7086.61 | C53: 0 | D53: 0 | E53: 0 | F53: 7000 | G53: 4837.49 | H53: 18924.1 | I53: 19882.133 | J53: 0 | K53: 18924.1
A54: 60 | B54: 7086.61 | C54: 0 | D54: 0 | E54: 0 | F54: 7000 | G54: 4837.49 | H54: 18924.1 | I54: 20379.186 | J54: 0 | K54: 18924.1
A55: 61 | B55: 7086.61 | C55: 0 | D55: 0 | E55: 0 | F55: 10000 | G55: 4837.49 | H55: 21924.1 | I55: 20888.666 | J55: 453.498 | K55: 21470.602
A56: 62 | B56: 7086.61 | C56: 0 | D56: 0 | E56: 0 | F56: 10000 | G56: 4837.49 | H56: 21924.1 | I56: 21410.882 | J56: 453.498 | K56: 21470.602
A57: 63 | B57: 7086.61 | C57: 0 | D57: 0 | E57: 0 | F57: 10000 | G57: 4837.49 | H57: 21924.1 | I57: 21946.154 | J57: 453.498 | K57: 21470.602
A58: 64 | B58: 7086.61 | C58: 0 | D58: 0 | E58: 0 | F58: 10000 | G58: 4837.49 | H58: 21924.1 | I58: 22494.808 | J58: 453.498 | K58: 21470.602
A59: 65 | B59: 7086.61 | C59: 0 | D59: 0 | E59: 0 | F59: 10000 | G59: 4837.49 | H59: 21924.1 | I59: 23057.178 | J59: 453.498 | K59: 21470.602
A60: 66 | B60: 7086.61 | C60: 0 | D60: 0 | E60: 0 | F60: 10000 | G60: 4837.49 | H60: 21924.1 | I60: 23633.608 | J60: 453.498 | K60: 21470.602
A61: 67 | B61: 7086.61 | C61: 0 | D61: 17722.965 | E61: 0 | F61: 10000 | G61: 4837.49 | H61: 39647.065 | I61: 24224.448 | J61: 3998.091 | K61: 35648.974
A62: 68 | B62: 7086.61 | C62: 0 | D62: 18431.883 | E62: 0 | F62: 10000 | G62: 4837.49 | H62: 40355.983 | I62: 24830.059 | J62: 4139.8747 | K62: 36216.109
... A83: 88 | B83: 22155.433 | C83: 0 | D83: 40386.526 | E83: 0 | F83: 10000 | G83: 9373.5066 | H83: 81915.466 | I83: 69482.12 | J83: 9438.0066 | K83: 72477.46
A84: 89 | B84: 40904.285 | C84: 133483.49 | D84: 136307.91 | E84: 21981.05 | F84: 111502.44 | G84: 6497.4927 | H84: 68344.104 | I84: 0.14753686 | J84: 4855.0691
A85: 90 | B85: 44415.693 | C85: 139715.61 | D85: 139715.61 | E85: 23227.474 | F85: 116488.14 | G85: 6497.4927 | H85: 70203.659 | I85: 0.1489265 | J85: 4979.0395
A86: 90 | B86: 18838.554 | C86: 118396.24 | D86: 147995.3 | E86: 18080.228 | F86: 100316.01

Sheet Person 2 Draw-down
A1: Pension 2 Draw-down
A3: Age | D3: 55 | E3: 56 | F3: 57 | G3: 58 | H3: 59 | I3: 60 | J3: 61 | K3: 62 | L3: 63 | M3: 64 | N3: 65 | O3: 66 | P3: 67 | Q3: 68 | R3: 69 | S3: 70 | T3: 71 | U3: 72 | V3: 73 | W3: 74 | X3: 75 | Y3: 76 | Z3: 77 | AA3: 78 | AB3: 79 | AC3: 80 | AD3: 81 | AE3: 82 | AF3: 83 | AG3: 84 | AH3: 85 | AI3: 86 | AJ3: 87 | AK3: 88 | AL3: 89 | AM3: 90 | AN3: 91 | AO3: 92 | AP3: 93 | AQ3: 94 | AR3: 95 | AS3: 96 | AT3: 97 | AU3: 98 | AV3: 99
A4: Year | D4: ='Person 2 Calculator'!$F$6 -> 2024 | E4: =D4+1 -> 2025 | F4: =E4+1 -> 2026 | G4: =F4+1 -> 2027 | H4: =G4+1 -> 2028 | I4: =H4+1 -> 2029 | J4: =I4+1 -> 2030 | K4: =J4+1 -> 2031 | L4: =K4+1 -> 2032 | ... AV4: =AU4+1 -> 2068
A5: ONGOING ASSET VALUES | D5: =LET( TargetYear, D4, StartYear, 'Person 2 Calculator'!$F$4, EndYear, 'Person 2 Calculator'!$F$5, SIPPflag, Income!$K$4, IF( SIPPflag = 0, IF(TargetYear < StartYear, 4, IF(TargetYear = StartYear, 5, IF(AND(TargetYear > StartYear, TargetYear < EndYear), 6, IF(TargetYear >= EndYear, 7, "") ) ) ), IFS( TargetYear < StartYear, 0, TargetYear = StartYear, 1, AND(TargetYear > StartYear, TargetYear < EndYear), 2, TargetYear >= EndYear, 3 ) ) ) -> 4 | E5: =LET( TargetYear, E4, StartYear, 'Person 2 Calculator'!$F$4, EndYear, 'Person 2 Calculator'!$F$5, SIPPflag, Income!$K$4, IF( SIPPflag = 0, IF(TargetYear < StartYear, 4, IF(TargetYear = StartYear, 5, IF(AND(TargetYear > StartYear, TargetYear < EndYear), 6, IF(TargetYear >= EndYear, 7, "") ) ) ), IFS( TargetYear < StartYear, 0, TargetYear = StartYear, 1, AND(TargetYear > StartYear, TargetYear < EndYear), 2, TargetYear >= EndYear, 3 ) ) ) -> 4 | F5: =LET( TargetYear, F4, StartYear, 'Person 2 Calculator'!$F$4, EndYear, 'Person 2 Calculator'!$F$5, SIPPflag, Income!$K$4, IF( SIPPflag = 0, IF(TargetYear < StartYear, 4, IF(TargetYear = StartYear, 5, IF(AND(TargetYear > StartYear, TargetYear < EndYear), 6, IF(TargetYear >= EndYear, 7, "") ) ) ), IFS( TargetYear < StartYear, 0, TargetYear = StartYear, 1, AND(TargetYear > StartYear, TargetYear < EndYear), 2, TargetYear >= EndYear, 3 ) ) ) -> 5 | G5: =LET( TargetYear, G4, StartYear, 'Person 2 Calculator'!$F$4, EndYear, 'Person 2 Calculator'!$F$5, SIPPflag, Income!$K$4, IF( SIPPflag = 0, IF(TargetYear < StartYear, 4, IF(TargetYear = StartYear, 5, IF(AND(TargetYear > StartYear, TargetYear < EndYear), 6, IF(TargetYear >= EndYear, 7, "") ) ) ), IFS( TargetYear < StartYear, 0, TargetYear = StartYear, 1, AND(TargetYear > StartYear, TargetYear < EndYear), 2, TargetYear >= EndYear, 3 ) ) ) -> 6 | H5: =LET( TargetYear, H4, StartYear, 'Person 2 Calculator'!$F$4, EndYear, 'Person 2 Calculator'!$F$5, SIPPflag, Income!$K$4, IF( SIPPflag = 0, IF(TargetYear < StartYear, 4, IF(TargetYear = StartYear, 5, IF(AND(TargetYear > StartYear, TargetYear < EndYear), 6, IF(TargetYear >= EndYear, 7, "") ) ) ), IFS( TargetYear < StartYear, 0, TargetYear = StartYear, 1, AND(TargetYear > StartYear, TargetYear < EndYear), 2, TargetYear >= EndYear, 3 ) ) ) -> 6 | I5: =LET( TargetYear, I4, StartYear, 'Person 2 Calculator'!$F$4, EndYear, 'Person 2 Calculator'!$F$5, SIPPflag, Income!$K$4, IF( SIPPflag = 0, IF(TargetYear < StartYear, 4, IF(TargetYear = StartYear, 5, IF(AND(TargetYear > StartYear, TargetYear < EndYear), 6, IF(TargetYear >= EndYear, 7, "") ) ) ), IFS( TargetYear < StartYear, 0, TargetYear = StartYear, 1, AND(TargetYear > StartYear, TargetYear < EndYear), 2, TargetYear >= EndYear, 3 ) ) ) -> 6 | J5: =LET( TargetYear, J4, StartYear, 'Person 2 Calculator'!$F$4, EndYear, 'Person 2 Calculator'!$F$5, SIPPflag, Income!$K$4, IF( SIPPflag = 0, IF(TargetYear < StartYear, 4, IF(TargetYear = StartYear, 5, IF(AND(TargetYear > StartYear, TargetYear < EndYear), 6, IF(TargetYear >= EndYear, 7, "") ) ) ), IFS( TargetYear < StartYear, 0, TargetYear = StartYear, 1, AND(TargetYear > StartYear, TargetYear < EndYear), 2, TargetYear >= EndYear, 3 ) ) ) -> 6 | K5: =LET( TargetYear, K4, StartYear, 'Person 2 Calculator'!$F$4, EndYear, 'Person 2 Calculator'!$F$5, SIPPflag, Income!$K$4, IF( SIPPflag = 0, IF(TargetYear < StartYear, 4, IF(TargetYear = StartYear, 5, IF(AND(TargetYear > StartYear, TargetYear < EndYear), 6, IF(TargetYear >= EndYear, 7, "") ) ) ), IFS( TargetYear < StartYear, 0, TargetYear = StartYear, 1, AND(TargetYear > StartYear, TargetYear < EndYear), 2, TargetYear >= EndYear, 3 ) ) ) -> 6 | ... AV5: =LET( TargetYear, AV4, StartYear, 'Person 2 Calculator'!$F$4, EndYear, 'Person 2 Calculator'!$F$5, SIPPflag, Income!$K$4, IF( SIPPflag = 0, IF(TargetYear < StartYear, 4, IF(TargetYear = StartYear, 5, IF(AND(TargetYear > StartYear, TargetYear < EndYear), 6, IF(TargetYear >= EndYear, 7, "") ) ) ), IFS( TargetYear < StartYear, 0, TargetYear = StartYear, 1, AND(TargetYear > StartYear, TargetYear < EndYear), 2, TargetYear >= EndYear, 3 ) ) ) -> 7
A6: SIPP Value | D6: =if(D5>3,, LET( CurrentYear, D4, PreviousYearValue, C6, ActionCode, N(D5), DeductionAmount, D7, InitialSeedValue, Income!$K$4, AnnualGrowthRate, Income!$L$4, FixedAnnualAddition, Income!$N$4, CalculationValue, IF(N(PreviousYearValue)=0, InitialSeedValue, PreviousYearValue), ProrataFactor, IF(CurrentYear = YEAR(TODAY()), (12 - MONTH(TODAY()) + 1) / 12, 1), GrowthAmount, CalculationValue * AnnualGrowthRate, IsYearInPast, CurrentYear < YEAR(TODAY()), IsStopCode, ActionCode = 3, IF(OR(IsYearInPast, IsStopCode), "", SWITCH(ActionCode, 0, CalculationValue + (GrowthAmount + FixedAnnualAddition) * ProrataFactor, 1, CalculationValue + (GrowthAmount - DeductionAmount) * ProrataFactor, 2, CalculationValue + (GrowthAmount - DeductionAmount) * ProrataFactor, "" ) ) ) ) | E6: =if(D6<0,D6, LET( CurrentYear, E4, PreviousYearValue, D6, ActionCode, N(E5), DeductionAmount, E7, InitialSeedValue, Income!$D$4, AnnualGrowthRate, Income!$E$4, FixedAnnualAddition, Income!$G$4, CalculationValue, IF(N(PreviousYearValue)=0, InitialSeedValue, PreviousYearValue), ProrataFactor, IF(CurrentYear = YEAR(TODAY()), (12 - MONTH(TODAY()) + 1) / 12, 1), GrowthAmount, CalculationValue * AnnualGrowthRate, IsYearInPast, CurrentYear < YEAR(TODAY()), IsStopCode, ActionCode = 3, IF(OR(IsYearInPast, IsStopCode), "", SWITCH(ActionCode, 0, CalculationValue + (GrowthAmount + FixedAnnualAddition) * ProrataFactor, 1, CalculationValue + (GrowthAmount - DeductionAmount) * ProrataFactor, 2, CalculationValue + (GrowthAmount - DeductionAmount) * ProrataFactor, "" ) ) ) ) | F6: =if(E6<0,E6, LET( CurrentYear, F4, PreviousYearValue, E6, ActionCode, N(F5), DeductionAmount, F7, InitialSeedValue, Income!$D$4, AnnualGrowthRate, Income!$E$4, FixedAnnualAddition, Income!$G$4, CalculationValue, IF(N(PreviousYearValue)=0, InitialSeedValue, PreviousYearValue), ProrataFactor, IF(CurrentYear = YEAR(TODAY()), (12 - MONTH(TODAY()) + 1) / 12, 1), GrowthAmount, CalculationValue * AnnualGrowthRate, IsYearInPast, CurrentYear < YEAR(TODAY()), IsStopCode, ActionCode = 3, IF(OR(IsYearInPast, IsStopCode), "", SWITCH(ActionCode, 0, CalculationValue + (GrowthAmount + FixedAnnualAddition) * ProrataFactor, 1, CalculationValue + (GrowthAmount - DeductionAmount) * ProrataFactor, 2, CalculationValue + (GrowthAmount - DeductionAmount) * ProrataFactor, "" ) ) ) ) | G6: =if(F6<0,F6, LET( CurrentYear, G4, PreviousYearValue, F6, ActionCode, N(G5), DeductionAmount, G7, InitialSeedValue, Income!$D$4, AnnualGrowthRate, Income!$E$4, FixedAnnualAddition, Income!$G$4, CalculationValue, IF(N(PreviousYearValue)=0, InitialSeedValue, PreviousYearValue), ProrataFactor, IF(CurrentYear = YEAR(TODAY()), (12 - MONTH(TODAY()) + 1) / 12, 1), GrowthAmount, CalculationValue * AnnualGrowthRate, IsYearInPast, CurrentYear < YEAR(TODAY()), IsStopCode, ActionCode = 3, IF(OR(IsYearInPast, IsStopCode), "", SWITCH(ActionCode, 0, CalculationValue + (GrowthAmount + FixedAnnualAddition) * ProrataFactor, 1, CalculationValue + (GrowthAmount - DeductionAmount) * ProrataFactor, 2, CalculationValue + (GrowthAmount - DeductionAmount) * ProrataFactor, "" ) ) ) ) | H6: =if(G6<0,G6, LET( CurrentYear, H4, PreviousYearValue, G6, ActionCode, N(H5), DeductionAmount, H7, InitialSeedValue, Income!$D$4, AnnualGrowthRate, Income!$E$4, FixedAnnualAddition, Income!$G$4, CalculationValue, IF(N(PreviousYearValue)=0, InitialSeedValue, PreviousYearValue), ProrataFactor, IF(CurrentYear = YEAR(TODAY()), (12 - MONTH(TODAY()) + 1) / 12, 1), GrowthAmount, CalculationValue * AnnualGrowthRate, IsYearInPast, CurrentYear < YEAR(TODAY()), IsStopCode, ActionCode = 3, IF(OR(IsYearInPast, IsStopCode), "", SWITCH(ActionCode, 0, CalculationValue + (GrowthAmount + FixedAnnualAddition) * ProrataFactor, 1, CalculationValue + (GrowthAmount - DeductionAmount) * ProrataFactor, 2, CalculationValue + (GrowthAmount - DeductionAmount) * ProrataFactor, "" ) ) ) ) | I6: =if(H6<0,H6, LET( CurrentYear, I4, PreviousYearValue, H6, ActionCode, N(I5), DeductionAmount, I7, InitialSeedValue, Income!$D$4, AnnualGrowthRate, Income!$E$4, FixedAnnualAddition, Income!$G$4, CalculationValue, IF(N(PreviousYearValue)=0, InitialSeedValue, PreviousYearValue), ProrataFactor, IF(CurrentYear = YEAR(TODAY()), (12 - MONTH(TODAY()) + 1) / 12, 1), GrowthAmount, CalculationValue * AnnualGrowthRate, IsYearInPast, CurrentYear < YEAR(TODAY()), IsStopCode, ActionCode = 3, IF(OR(IsYearInPast, IsStopCode), "", SWITCH(ActionCode, 0, CalculationValue + (GrowthAmount + FixedAnnualAddition) * ProrataFactor, 1, CalculationValue + (GrowthAmount - DeductionAmount) * ProrataFactor, 2, CalculationValue + (GrowthAmount - DeductionAmount) * ProrataFactor, "" ) ) ) ) | J6: =if(I6<0,I6, LET( CurrentYear, J4, PreviousYearValue, I6, ActionCode, N(J5), DeductionAmount, J7, InitialSeedValue, Income!$D$4, AnnualGrowthRate, Income!$E$4, FixedAnnualAddition, Income!$G$4, CalculationValue, IF(N(PreviousYearValue)=0, InitialSeedValue, PreviousYearValue), ProrataFactor, IF(CurrentYear = YEAR(TODAY()), (12 - MONTH(TODAY()) + 1) / 12, 1), GrowthAmount, CalculationValue * AnnualGrowthRate, IsYearInPast, CurrentYear < YEAR(TODAY()), IsStopCode, ActionCode = 3, IF(OR(IsYearInPast, IsStopCode), "", SWITCH(ActionCode, 0, CalculationValue + (GrowthAmount + FixedAnnualAddition) * ProrataFactor, 1, CalculationValue + (GrowthAmount - DeductionAmount) * ProrataFactor, 2, CalculationValue + (GrowthAmount - DeductionAmount) * ProrataFactor, "" ) ) ) ) | K6: =if(J6<0,J6, LET( CurrentYear, K4, PreviousYearValue, J6, ActionCode, N(K5), DeductionAmount, K7, InitialSeedValue, Income!$D$4, AnnualGrowthRate, Income!$E$4, FixedAnnualAddition, Income!$G$4, CalculationValue, IF(N(PreviousYearValue)=0, InitialSeedValue, PreviousYearValue), ProrataFactor, IF(CurrentYear = YEAR(TODAY()), (12 - MONTH(TODAY()) + 1) / 12, 1), GrowthAmount, CalculationValue * AnnualGrowthRate, IsYearInPast, CurrentYear < YEAR(TODAY()), IsStopCode, ActionCode = 3, IF(OR(IsYearInPast, IsStopCode), "", SWITCH(ActionCode, 0, CalculationValue + (GrowthAmount + FixedAnnualAddition) * ProrataFactor, 1, CalculationValue + (GrowthAmount - DeductionAmount) * ProrataFactor, 2, CalculationValue + (GrowthAmount - DeductionAmount) * ProrataFactor, "" ) ) ) ) | L6: =if(K6<0,K6, LET( CurrentYear, L4, PreviousYearValue, K6, ActionCode, N(L5), DeductionAmount, L7, InitialSeedValue, Income!$D$4, AnnualGrowthRate, Income!$E$4, FixedAnnualAddition, Income!$G$4, CalculationValue, IF(N(PreviousYearValue)=0, InitialSeedValue, PreviousYearValue), ProrataFactor, IF(CurrentYear = YEAR(TODAY()), (12 - MONTH(TODAY()) + 1) / 12, 1), GrowthAmount, CalculationValue * AnnualGrowthRate, IsYearInPast, CurrentYear < YEAR(TODAY()), IsStopCode, ActionCode = 3, IF(OR(IsYearInPast, IsStopCode), "", SWITCH(ActionCode, 0, CalculationValue + (GrowthAmount + FixedAnnualAddition) * ProrataFactor, 1, CalculationValue + (GrowthAmount - DeductionAmount) * ProrataFactor, 2, CalculationValue + (GrowthAmount - DeductionAmount) * ProrataFactor, "" ) ) ) ) | ... AV6: =if(AU6<0,AU6, LET( CurrentYear, AV4, PreviousYearValue, AU6, ActionCode, N(AV5), DeductionAmount, AV7, InitialSeedValue, Income!$D$4, AnnualGrowthRate, Income!$E$4, FixedAnnualAddition, Income!$G$4, CalculationValue, IF(N(PreviousYearValue)=0, InitialSeedValue, PreviousYearValue), ProrataFactor, IF(CurrentYear = YEAR(TODAY()), (12 - MONTH(TODAY()) + 1) / 12, 1), GrowthAmount, CalculationValue * AnnualGrowthRate, IsYearInPast, CurrentYear < YEAR(TODAY()), IsStopCode, ActionCode = 3, IF(OR(IsYearInPast, IsStopCode), "", SWITCH(ActionCode, 0, CalculationValue + (GrowthAmount + FixedAnnualAddition) * ProrataFactor, 1, CalculationValue + (GrowthAmount - DeductionAmount) * ProrataFactor, 2, CalculationValue + (GrowthAmount - DeductionAmount) * ProrataFactor, "" ) ) ) )
A7: Annual SIPP Draw-down | D7: =IF(OR(D5=1,D5=2,D5=5,D5=6), D26-D12-D14-D16-D18-D20-D22, ) | E7: =LET( base, E26 - E12 - E14 - E16 - E18 - E20 - E22, action, N(E5), IFS( action = 0, "", action = 1, base, action = 2, IF( ISNUMBER(SEARCH("Smooth", 'Person 2 Calculator'!$F$20)), MAX(base, 0), D7 ), action >= 3, "" ) ) | F7: =LET( base, F26 - F12 - F14 - F16 - F18 - F20 - F22, action, N(F5), IFS( action = 0, "", action = 1, base, action = 2, IF( ISNUMBER(SEARCH("Smooth", 'Person 2 Calculator'!$F$20)), MAX(base, 0), E7 ), action >= 3, "" ) ) | G7: =LET( base, G26 - G12 - G14 - G16 - G18 - G20 - G22, action, N(G5), IFS( action = 0, "", action = 1, base, action = 2, IF( ISNUMBER(SEARCH("Smooth", 'Person 2 Calculator'!$F$20)), MAX(base, 0), F7 ), action >= 3, "" ) ) | H7: =LET( base, H26 - H12 - H14 - H16 - H18 - H20 - H22, action, N(H5), IFS( action = 0, "", action = 1, base, action = 2, IF( ISNUMBER(SEARCH("Smooth", 'Person 2 Calculator'!$F$20)), MAX(base, 0), G7 ), action >= 3, "" ) ) | I7: =IF(OR(I5=1, I5=2), I26-I12-I14-I16-I18-I20-I22, ) | J7: =LET( base, J26 - J12 - J14 - J16 - J18 - J20 - J22, action, N(J5), IFS( action = 0, "", action = 1, base, action = 2, IF( ISNUMBER(SEARCH("Smooth", 'Person 2 Calculator'!$F$20)), MAX(base, 0), I7 ), action >= 3, "" ) ) | K7: =LET( base, K26 - K12 - K14 - K16 - K18 - K20 - K22, action, N(K5), IFS( action = 0, "", action = 1, base, action = 2, IF( ISNUMBER(SEARCH("Smooth", 'Person 2 Calculator'!$F$20)), MAX(base, 0), J7 ), action >= 3, "" ) ) | L7: =LET( base, L26 - L12 - L14 - L16 - L18 - L20 - L22, action, N(L5), IFS( action = 0, "", action = 1, base, action = 2, IF( ISNUMBER(SEARCH("Smooth", 'Person 2 Calculator'!$F$20)), MAX(base, 0), K7 ), action >= 3, "" ) ) | M7: =LET( base, M26 - M12 - M14 - M16 - M18 - M20 - M22, action, N(M5), IFS( action = 0, "", action = 1, base, action = 2, IF( ISNUMBER(SEARCH("Smooth", 'Person 2 Calculator'!$F$20)), MAX(base, 0), L7 ), action >= 3, "" ) ) | N7: =IF(OR(N5=1, N5=2), N26-N12-N14-N16-N18-N20-N22, ) | O7: =LET( base, O26 - O12 - O14 - O16 - O18 - O20 - O22, action, N(O5), IFS( action = 0, "", action = 1, base, action = 2, IF( ISNUMBER(SEARCH("Smooth", 'Person 2 Calculator'!$F$20)), MAX(base, 0), N7 ), action >= 3, "" ) ) | P7: =LET( base, P26 - P12 - P14 - P16 - P18 - P20 - P22, raw, IFS( P5 = 0, "", P5 = 1, base, P5 = 2, IF( ISNUMBER(SEARCH("Smooth", 'Person 2 Calculator'!$F$20)), base, O7 - P16 ), P5 >= 3, "" ), IF(ISNUMBER(raw), MAX(raw, 0), raw) ) | Q7: =LET( base, Q26 - Q12 - Q14 - Q16 - Q18 - Q20 - Q22, action, N(Q5), IFS( action = 0, "", action = 1, base, action = 2, IF( ISNUMBER(SEARCH("Smooth", 'Person 2 Calculator'!$F$20)), MAX(base, 0), P7 ), action >= 3, "" ) ) | R7: =LET( base, R26 - R12 - R14 - R16 - R18 - R20 - R22, action, N(R5), IFS( action = 0, "", action = 1, base, action = 2, IF( ISNUMBER(SEARCH("Smooth", 'Person 2 Calculator'!$F$20)), MAX(base, 0), Q7 ), action >= 3, "" ) ) | S7: =IF( OR(S5 = 1, S5 = 2), MAX(0, (1-'Person 2 Calculator'!$F$16)*S26 - S12 - S14 - S16 - S18 - S20 - S22), "" ) | T7: =LET( base, (1-'Person 2 Calculator'!$F$16)*T26 - T12 - T14 - T16 - T18 - T20 - T22, action, N(T5), IFS( action = 0, "", action = 1, base, action = 2, IF( ISNUMBER(SEARCH("Smooth", 'Person 2 Calculator'!$F$20)), MAX(base, 0), S7 ), action >= 3, "" ) ) | U7: =LET( base, (1-'Person 2 Calculator'!$F$16)*U26 - U12 - U14 - U16 - U18 - U20 - U22, action, N(U5), IFS( action = 0, "", action = 1, base, action = 2, IF( ISNUMBER(SEARCH("Smooth", 'Person 2 Calculator'!$F$20)), MAX(base, 0), T7 ), action >= 3, "" ) ) | V7: =LET( base, (1-'Person 2 Calculator'!$F$16)*V26 - V12 - V14 - V16 - V18 - V20 - V22, action, N(V5), IFS( action = 0, "", action = 1, base, action = 2, IF( ISNUMBER(SEARCH("Smooth", 'Person 2 Calculator'!$F$20)), MAX(base, 0), U7 ), action >= 3, "" ) ) | W7: =LET( base, (1-'Person 2 Calculator'!$F$16)*W26 - W12 - W14 - W16 - W18 - W20 - W22, action, N(W5), IFS( action = 0, "", action = 1, base, action = 2, IF( ISNUMBER(SEARCH("Smooth", 'Person 2 Calculator'!$F$20)), MAX(base, 0), V7 ), action >= 3, "" ) ) | X7: =IF( OR(X5 = 1, X5 = 2), MAX(0, (1-'Person 2 Calculator'!$F$16)*X26 - X12 - X14 - X16 - X18 - X20 - X22), "" ) | Y7: =LET( base, (1-'Person 2 Calculator'!$F$16)*Y26 - Y12 - Y14 - Y16 - Y18 - Y20 - Y22, action, N(Y5), IFS( action = 0, "", action = 1, base, action = 2, IF( ISNUMBER(SEARCH("Smooth", 'Person 2 Calculator'!$F$20)), MAX(base, 0), X7 ), action >= 3, "" ) ) | Z7: =LET( base, (1-'Person 2 Calculator'!$F$16)*Z26 - Z12 - Z14 - Z16 - Z18 - Z20 - Z22, action, N(Z5), IFS( action = 0, "", action = 1, base, action = 2, IF( ISNUMBER(SEARCH("Smooth", 'Person 2 Calculator'!$F$20)), MAX(base, 0), Y7 ), action >= 3, "" ) ) | AA7: =LET( base, (1-'Person 2 Calculator'!$F$16)*AA26 - AA12 - AA14 - AA16 - AA18 - AA20 - AA22, action, N(AA5), IFS( action = 0, "", action = 1, base, action = 2, IF( ISNUMBER(SEARCH("Smooth", 'Person 2 Calculator'!$F$20)), MAX(base, 0), Z7 ), action >= 3, "" ) ) | AB7: =LET( base, (1-'Person 2 Calculator'!$F$16)*AB26 - AB12 - AB14 - AB16 - AB18 - AB20 - AB22, action, N(AB5), IFS( action = 0, "", action = 1, base, action = 2, IF( ISNUMBER(SEARCH("Smooth", 'Person 2 Calculator'!$F$20)), MAX(base, 0), AA7 ), action >= 3, "" ) ) | AC7: =IF( OR(AC5 = 1, AC5 = 2), MAX(0, (1-'Person 2 Calculator'!$F$17)*AC26 - AC12 - AC14 - AC16 - AC18 - AC20 - AC22), "" ) | AD7: =LET( base, (1-'Person 2 Calculator'!$F$17)*AD26 - AD12 - AD14 - AD16 - AD18 - AD20 - AD22, action, N(AD5), IFS( action = 0, "", action = 1, base, action = 2, IF( ISNUMBER(SEARCH("Smooth", 'Person 2 Calculator'!$F$20)), MAX(base, 0), AC7 ), action >= 3, "" ) ) | AE7: =LET( base, (1-'Person 2 Calculator'!$F$17)*AE26 - AE12 - AE14 - AE16 - AE18 - AE20 - AE22, action, N(AE5), IFS( action = 0, "", action = 1, base, action = 2, IF( ISNUMBER(SEARCH("Smooth", 'Person 2 Calculator'!$F$20)), MAX(base, 0), AD7 ), action >= 3, "" ) ) | AF7: =LET( base, (1-'Person 2 Calculator'!$F$17)*AF26 - AF12 - AF14 - AF16 - AF18 - AF20 - AF22, action, N(AF5), IFS( action = 0, "", action = 1, base, action = 2, IF( ISNUMBER(SEARCH("Smooth", 'Person 2 Calculator'!$F$20)), MAX(base, 0), AE7 ), action >= 3, "" ) ) | AG7: =LET( base, (1-'Person 2 Calculator'!$F$17)*AG26 - AG12 - AG14 - AG16 - AG18 - AG20 - AG22, action, N(AG5), IFS( action = 0, "", action = 1, base, action = 2, IF( ISNUMBER(SEARCH("Smooth", 'Person 2 Calculator'!$F$20)), MAX(base, 0), AF7 ), action >= 3, "" ) ) | AH7: =IF( OR(AH5 = 1, AH5 = 2), MAX(0, (1-'Person 2 Calculator'!$F$17)*AH26 - AH12 - AH14 - AH16 - AH18 - AH20 - AH22), "" ) | AI7: =LET( base, (1-'Person 2 Calculator'!$F$17)*AI26 - AI12 - AI14 - AI16 - AI18 - AI20 - AI22, action, N(AI5), IFS( action = 0, "", action = 1, base, action = 2, IF( ISNUMBER(SEARCH("Smooth", 'Person 2 Calculator'!$F$20)), MAX(base, 0), AH7 ), action >= 3, "" ) ) | AJ7: =LET( base, (1-'Person 2 Calculator'!$F$17)*AJ26 - AJ12 - AJ14 - AJ16 - AJ18 - AJ20 - AJ22, action, N(AJ5), IFS( action = 0, "", action = 1, base, action = 2, IF( ISNUMBER(SEARCH("Smooth", 'Person 2 Calculator'!$F$20)), MAX(base, 0), AI7 ), action >= 3, "" ) ) | AK7: =LET( base, (1-'Person 2 Calculator'!$F$17)*AK26 - AK12 - AK14 - AK16 - AK18 - AK20 - AK22, action, N(AK5), IFS( action = 0, "", action = 1, base, action = 2, IF( ISNUMBER(SEARCH("Smooth", 'Person 2 Calculator'!$F$20)), MAX(base, 0), AJ7 ), action >= 3, "" ) ) | AL7: =LET( base, (1-'Person 2 Calculator'!$F$17)*AL26 - AL12 - AL14 - AL16 - AL18 - AL20 - AL22, action, N(AL5), IFS( action = 0, "", action = 1, base, action = 2, IF( ISNUMBER(SEARCH("Smooth", 'Person 2 Calculator'!$F$20)), MAX(base, 0), AK7 ), action >= 3, "" ) ) | AM7: =IF( OR(AM5 = 1, AM5 = 2), MAX(0, (1-'Person 2 Calculator'!$F$17)*AM26 - AM12 - AM14 - AM16 - AM18 - AM20 - AM22), "" ) | AN7: =LET( base, (1-'Person 2 Calculator'!$F$17)*AN26 - AN12 - AN14 - AN16 - AN18 - AN20 - AN22, action, N(AN5), IFS( action = 0, "", action = 1, base, action = 2, IF( ISNUMBER(SEARCH("Smooth", 'Person 2 Calculator'!$F$20)), MAX(base, 0), AM7 ), action >= 3, "" ) ) | AO7: =LET( base, (1-'Person 2 Calculator'!$F$17)*AO26 - AO12 - AO14 - AO16 - AO18 - AO20 - AO22, action, N(AO5), IFS( action = 0, "", action = 1, base, action = 2, IF( ISNUMBER(SEARCH("Smooth", 'Person 2 Calculator'!$F$20)), MAX(base, 0), AN7 ), action >= 3, "" ) ) | AP7: =LET( base, (1-'Person 2 Calculator'!$F$17)*AP26 - AP12 - AP14 - AP16 - AP18 - AP20 - AP22, action, N(AP5), IFS( action = 0, "", action = 1, base, action = 2, IF( ISNUMBER(SEARCH("Smooth", 'Person 2 Calculator'!$F$20)), MAX(base, 0), AO7 ), action >= 3, "" ) ) | AQ7: =LET( base, (1-'Person 2 Calculator'!$F$17)*AQ26 - AQ12 - AQ14 - AQ16 - AQ18 - AQ20 - AQ22, action, N(AQ5), IFS( action = 0, "", action = 1, base, action = 2, IF( ISNUMBER(SEARCH("Smooth", 'Person 2 Calculator'!$F$20)), MAX(base, 0), AP7 ), action >= 3, "" ) ) | AR7: =IF( OR(AR5 = 1, AR5 = 2), MAX(0, (1-'Person 2 Calculator'!$F$17)*AR26 - AR12 - AR14 - AR16 - AR18 - AR20 - AR22), "" ) | AS7: =LET( base, (1-'Person 2 Calculator'!$F$17)*AS26 - AS12 - AS14 - AS16 - AS18 - AS20 - AS22, action, N(AS5), IFS( action = 0, "", action = 1, base, action = 2, IF( ISNUMBER(SEARCH("Smooth", 'Person 2 Calculator'!$F$20)), MAX(base, 0), AR7 ), action >= 3, "" ) ) | AT7: =LET( base, (1-'Person 2 Calculator'!$F$17)*AT26 - AT12 - AT14 - AT16 - AT18 - AT20 - AT22, action, N(AT5), IFS( action = 0, "", action = 1, base, action = 2, IF( ISNUMBER(SEARCH("Smooth", 'Person 2 Calculator'!$F$20)), MAX(base, 0), AS7 ), action >= 3, "" ) ) | AU7: =LET( base, (1-'Person 2 Calculator'!$F$17)*AU26 - AU12 - AU14 - AU16 - AU18 - AU20 - AU22, action, N(AU5), IFS( action = 0, "", action = 1, base, action = 2, IF( ISNUMBER(SEARCH("Smooth", 'Person 2 Calculator'!$F$20)), MAX(base, 0), AT7 ), action >= 3, "" ) ) | AV7: =LET( base, (1-'Person 2 Calculator'!$F$17)*AV26 - AV12 - AV14 - AV16 - AV18 - AV20 - AV22, action, N(AV5), IFS( action = 0, "", action = 1, base, action = 2, IF( ISNUMBER(SEARCH("Smooth", 'Person 2 Calculator'!$F$20)), MAX(base, 0), AU7 ), action >= 3, "" ) )
A8: Taxable draw-down (75%) | D8: =if(N(D7)>0,D7*0.75,) | E8: =if(N(E7)>0,E7*0.75,) | F8: =if(N(F7)>0,F7*0.75,) | G8: =if(N(G7)>0,G7*0.75,) | H8: =if(N(H7)>0,H7*0.75,) | I8: =if(N(I7)>0,I7*0.75,) | J8: =if(N(J7)>0,J7*0.75,) | K8: =if(N(K7)>0,K7*0.75,) | ... AV8: =if(N(AV7)>0,AV7*0.75,)
A9: Tax-free draw-down (25%) | D9: =if(N(D7)>0,D7*0.25,) | E9: =if(N(E7)>0,E7*0.25,) | F9: =if(N(F7)>0,F7*0.25,) | G9: =if(N(G7)>0,G7*0.25,) | H9: =if(N(H7)>0,H7*0.25,) | I9: =if(N(I7)>0,I7*0.25,) | J9: =if(N(J7)>0,J7*0.25,) | K9: =if(N(K7)>0,K7*0.25,) | ... AV9: =if(N(AV7)>0,AV7*0.25,)
A10: Accumulated tax free draw-down | D10: =D9 | E10: =if(OR(E5=1,E5=2),D10+E9,) | F10: =if(OR(F5=1,F5=2),E10+F9,) | G10: =if(OR(G5=1,G5=2),F10+G9,) | H10: =if(OR(H5=1,H5=2),G10+H9,) | I10: =if(OR(I5=1,I5=2),H10+I9,) | J10: =if(OR(J5=1,J5=2),I10+J9,) | K10: =if(OR(K5=1,K5=2),J10+K9,) | L10: =if(OR(L5=1,L5=2),K10+L9,) | ... AV10: =if(OR(AV5=1,AV5=2),AU10+AV9,)
A11: Monthly SIPP draw-down | D11: =if(N(D7)>0,D7/12,) | E11: =if(N(E7)>0,E7/12,) | F11: =if(N(F7)>0,F7/12,) | G11: =if(N(G7)>0,G7/12,) | H11: =if(N(H7)>0,H7/12,) | I11: =if(N(I7)>0,I7/12,) | J11: =if(N(J7)>0,J7/12,) | K11: =if(N(K7)>0,K7/12,) | ... AV11: =if(N(AV7)>0,AV7/12,)
A12: Annual ISAs Draw-down | D12: =IF(OR(D5=1,D5=2,D5=5,D5=6), Income!$M$14+Income!$M$15,) | E12: =IF(OR(E5=1,E5=2,E5=5,E5=6), Income!$M$14+Income!$M$15,) | F12: =IF(OR(F5=1,F5=2,F5=5,F5=6), Income!$M$14+Income!$M$15,) -> 7086.61 | G12: =IF(OR(G5=1,G5=2,G5=5,G5=6), Income!$M$14+Income!$M$15,) -> 7086.61 | H12: =IF(OR(H5=1,H5=2,H5=5,H5=6), Income!$M$14+Income!$M$15,) -> 7086.61 | I12: =IF(OR(I5=1,I5=2,I5=5,I5=6), Income!$M$14+Income!$M$15,) -> 7086.61 | J12: =IF(OR(J5=1,J5=2,J5=5,J5=6), Income!$M$14+Income!$M$15,) -> 7086.61 | K12: =IF(OR(K5=1,K5=2,K5=5,K5=6), Income!$M$14+Income!$M$15,) -> 7086.61 | ... AV12: =IF(OR(AV5=1,AV5=2,AV5=5,AV5=6), Income!$M$14+Income!$M$15,)
A13: Monthly ISA draw-down | D13: =if(D12>0,D12/12,) | E13: =if(E12>0,E12/12,) | F13: =if(F12>0,F12/12,) -> 590.55083 | G13: =if(G12>0,G12/12,) -> 590.55083 | H13: =if(H12>0,H12/12,) -> 590.55083 | I13: =if(I12>0,I12/12,) -> 590.55083 | J13: =if(J12>0,J12/12,) -> 590.55083 | K13: =if(K12>0,K12/12,) -> 590.55083 | ... AV13: =if(AV12>0,AV12/12,)
A14: Annual Rent | D14: =if(D5=0,, if(OR(D5=1, D5=5),Income!$K$18, if(OR(D5=2,D5=6),C14*(1+Income!$L$18), if(D5=3,,)))) | E14: =if(E5=0,, if(OR(E5=1, E5=5),Income!$K$18, if(OR(E5=2,E5=6),D14*(1+Income!$L$18), if(E5=3,,)))) | F14: =if(F5=0,, if(OR(F5=1, F5=5),Income!$K$18, if(OR(F5=2,F5=6),E14*(1+Income!$L$18), if(F5=3,,)))) -> 0 | G14: =if(G5=0,, if(OR(G5=1, G5=5),Income!$K$18, if(OR(G5=2,G5=6),F14*(1+Income!$L$18), if(G5=3,,)))) -> 0 | H14: =if(H5=0,, if(OR(H5=1, H5=5),Income!$K$18, if(OR(H5=2,H5=6),G14*(1+Income!$L$18), if(H5=3,,)))) -> 0 | I14: =if(I5=0,, if(OR(I5=1, I5=5),Income!$K$18, if(OR(I5=2,I5=6),H14*(1+Income!$L$18), if(I5=3,,)))) -> 0 | J14: =if(J5=0,, if(OR(J5=1, J5=5),Income!$K$18, if(OR(J5=2,J5=6),I14*(1+Income!$L$18), if(J5=3,,)))) -> 0 | K14: =if(K5=0,, if(OR(K5=1, K5=5),Income!$K$18, if(OR(K5=2,K5=6),J14*(1+Income!$L$18), if(K5=3,,)))) -> 0 | ... AV14: =if(AV5=0,, if(OR(AV5=1, AV5=5),Income!$K$18, if(OR(AV5=2,AV5=6),AU14*(1+Income!$L$18), if(AV5=3,,))))
A15: Monthly Rent | D15: =if(D14>0,D14/12,) | E15: =if(E14>0,E14/12,) | F15: =if(F14>0,F14/12,) | G15: =if(G14>0,G14/12,) | H15: =if(H14>0,H14/12,) | I15: =if(I14>0,I14/12,) | J15: =if(J14>0,J14/12,) | K15: =if(K14>0,K14/12,) | ... AV15: =if(AV14>0,AV14/12,)
A16: Annual State Pension | P16: =Income!$D$21 -> 17722.965 | Q16: =IF(OR(Q5<3,Q5=5,Q5=6),P16*(1+'Person 2 Calculator'!$F$19),) -> 18431.883 | R16: =IF(OR(R5<3,R5=5,R5=6),Q16*(1+'Person 2 Calculator'!$F$19),) -> 19169.159 | S16: =IF(OR(S5<3,S5=5,S5=6),R16*(1+'Person 2 Calculator'!$F$19),) -> 19935.925 | T16: =IF(OR(T5<3,T5=5,T5=6),S16*(1+'Person 2 Calculator'!$F$19),) -> 20733.362 | U16: =IF(OR(U5<3,U5=5,U5=6),T16*(1+'Person 2 Calculator'!$F$19),) -> 21562.697 | V16: =IF(OR(V5<3,V5=5,V5=6),U16*(1+'Person 2 Calculator'!$F$19),) -> 22425.204 | W16: =IF(OR(W5<3,W5=5,W5=6),V16*(1+'Person 2 Calculator'!$F$19),) -> 23322.213 | X16: =IF(OR(X5<3,X5=5,X5=6),W16*(1+'Person 2 Calculator'!$F$19),) -> 24255.101 | ... AV16: =IF(OR(AV5<3,AV5=5,AV5=6),AU16*(1+'Person 2 Calculator'!$F$19),)
A17: Monthly State Pension | P17: =if(P16>0,P16/12,) -> 1476.9137 | Q17: =if(Q16>0,Q16/12,) -> 1535.9903 | R17: =if(R16>0,R16/12,) -> 1597.4299 | S17: =if(S16>0,S16/12,) -> 1661.3271 | T17: =if(T16>0,T16/12,) -> 1727.7802 | U17: =if(U16>0,U16/12,) -> 1796.8914 | V17: =if(V16>0,V16/12,) -> 1868.767 | W17: =if(W16>0,W16/12,) -> 1943.5177 | ... AV17: =if(AV16>0,AV16/12,)
A18: Annual Annuities | D18: =IFERROR(__xludf.DUMMYFUNCTION("IF( OR(D5=1, D5=2, D5=5,D5=6), SUM( FILTER( Income!$K$6:$K$8, D4 >= Income!$M$6:$M$8 ) ) ,)"),"") | E18: =IFERROR(__xludf.DUMMYFUNCTION("IF( OR(E5=1, E5=2, E5=5,E5=6), SUM( FILTER( Income!$K$6:$K$8, E4 >= Income!$M$6:$M$8 ) ) ,)"),"") | F18: =IFERROR(__xludf.DUMMYFUNCTION("IF( OR(F5=1, F5=2, F5=5,F5=6), SUM( FILTER( Income!$K$6:$K$8, F4 >= Income!$M$6:$M$8 ) ) ,)"),0.0) -> 0 | G18: =IFERROR(__xludf.DUMMYFUNCTION("IF( OR(G5=1, G5=2, G5=5,G5=6), SUM( FILTER( Income!$K$6:$K$8, G4 >= Income!$M$6:$M$8 ) ) ,)"),0.0) -> 0 | H18: =IFERROR(__xludf.DUMMYFUNCTION("IF( OR(H5=1, H5=2, H5=5,H5=6), SUM( FILTER( Income!$K$6:$K$8, H4 >= Income!$M$6:$M$8 ) ) ,)"),0.0) -> 0 | I18: =IFERROR(__xludf.DUMMYFUNCTION("IF( OR(I5=1, I5=2, I5=5,I5=6), SUM( FILTER( Income!$K$6:$K$8, I4 >= Income!$M$6:$M$8 ) ) ,)"),0.0) -> 0 | J18: =IFERROR(__xludf.DUMMYFUNCTION("IF( OR(J5=1, J5=2, J5=5,J5=6), SUM( FILTER( Income!$K$6:$K$8, J4 >= Income!$M$6:$M$8 ) ) ,)"),0.0) -> 0 | K18: =IFERROR(__xludf.DUMMYFUNCTION("IF( OR(K5=1, K5=2, K5=5,K5=6), SUM( FILTER( Income!$K$6:$K$8, K4 >= Income!$M$6:$M$8 ) ) ,)"),0.0) -> 0 | L18: =IFERROR(__xludf.DUMMYFUNCTION("IF( OR(L5=1, L5=2, L5=5,L5=6), SUM( FILTER( Income!$K$6:$K$8, L4 >= Income!$M$6:$M$8 ) ) ,)"),0.0) -> 0 | M18: =IFERROR(__xludf.DUMMYFUNCTION("IF( OR(M5=1, M5=2, M5=5,M5=6), SUM( FILTER( Income!$K$6:$K$8, M4 >= Income!$M$6:$M$8 ) ) ,)"),0.0) -> 0 | N18: =IFERROR(__xludf.DUMMYFUNCTION("IF( OR(N5=1, N5=2, N5=5,N5=6), SUM( FILTER( Income!$K$6:$K$8, N4 >= Income!$M$6:$M$8 ) ) ,)"),0.0) -> 0 | O18: =IFERROR(__xludf.DUMMYFUNCTION("IF( OR(O5=1, O5=2, O5=5,O5=6), SUM( FILTER( Income!$K$6:$K$8, O4 >= Income!$M$6:$M$8 ) ) ,)"),0.0) -> 0 | P18: =IFERROR(__xludf.DUMMYFUNCTION("IF( OR(P5=1, P5=2, P5=5,P5=6), SUM( FILTER( Income!$K$6:$K$8, P4 >= Income!$M$6:$M$8 ) ) ,)"),0.0) -> 0 | Q18: =IFERROR(__xludf.DUMMYFUNCTION("IF( OR(Q5=1, Q5=2, Q5=5,Q5=6), SUM( FILTER( Income!$K$6:$K$8, Q4 >= Income!$M$6:$M$8 ) ) ,)"),0.0) -> 0 | R18: =IFERROR(__xludf.DUMMYFUNCTION("IF( OR(R5=1, R5=2, R5=5,R5=6), SUM( FILTER( Income!$K$6:$K$8, R4 >= Income!$M$6:$M$8 ) ) ,)"),0.0) -> 0 | S18: =IFERROR(__xludf.DUMMYFUNCTION("IF( OR(S5=1, S5=2, S5=5,S5=6), SUM( FILTER( Income!$K$6:$K$8, S4 >= Income!$M$6:$M$8 ) ) ,)"),0.0) -> 0 | T18: =IFERROR(__xludf.DUMMYFUNCTION("IF( OR(T5=1, T5=2, T5=5,T5=6), SUM( FILTER( Income!$K$6:$K$8, T4 >= Income!$M$6:$M$8 ) ) ,)"),0.0) -> 0 | U18: =IFERROR(__xludf.DUMMYFUNCTION("IF( OR(U5=1, U5=2, U5=5,U5=6), SUM( FILTER( Income!$K$6:$K$8, U4 >= Income!$M$6:$M$8 ) ) ,)"),0.0) -> 0 | V18: =IFERROR(__xludf.DUMMYFUNCTION("IF( OR(V5=1, V5=2, V5=5,V5=6), SUM( FILTER( Income!$K$6:$K$8, V4 >= Income!$M$6:$M$8 ) ) ,)"),0.0) -> 0 | W18: =IFERROR(__xludf.DUMMYFUNCTION("IF( OR(W5=1, W5=2, W5=5,W5=6), SUM( FILTER( Income!$K$6:$K$8, W4 >= Income!$M$6:$M$8 ) ) ,)"),0.0) -> 0 | X18: =IFERROR(__xludf.DUMMYFUNCTION("IF( OR(X5=1, X5=2, X5=5,X5=6), SUM( FILTER( Income!$K$6:$K$8, X4 >= Income!$M$6:$M$8 ) ) ,)"),0.0) -> 0 | Y18: =IFERROR(__xludf.DUMMYFUNCTION("IF( OR(Y5=1, Y5=2, Y5=5,Y5=6), SUM( FILTER( Income!$K$6:$K$8, Y4 >= Income!$M$6:$M$8 ) ) ,)"),0.0) -> 0 | Z18: =IFERROR(__xludf.DUMMYFUNCTION("IF( OR(Z5=1, Z5=2, Z5=5,Z5=6), SUM( FILTER( Income!$K$6:$K$8, Z4 >= Income!$M$6:$M$8 ) ) ,)"),0.0) -> 0 | AA18: =IFERROR(__xludf.DUMMYFUNCTION("IF( OR(AA5=1, AA5=2, AA5=5,AA5=6), SUM( FILTER( Income!$K$6:$K$8, AA4 >= Income!$M$6:$M$8 ) ) ,)"),0.0) -> 0 | AB18: =IFERROR(__xludf.DUMMYFUNCTION("IF( OR(AB5=1, AB5=2, AB5=5,AB5=6), SUM( FILTER( Income!$K$6:$K$8, AB4 >= Income!$M$6:$M$8 ) ) ,)"),0.0) -> 0 | AC18: =IFERROR(__xludf.DUMMYFUNCTION("IF( OR(AC5=1, AC5=2, AC5=5,AC5=6), SUM( FILTER( Income!$K$6:$K$8, AC4 >= Income!$M$6:$M$8 ) ) ,)"),0.0) -> 0 | AD18: =IFERROR(__xludf.DUMMYFUNCTION("IF( OR(AD5=1, AD5=2, AD5=5,AD5=6), SUM( FILTER( Income!$K$6:$K$8, AD4 >= Income!$M$6:$M$8 ) ) ,)"),0.0) -> 0 | AE18: =IFERROR(__xludf.DUMMYFUNCTION("IF( OR(AE5=1, AE5=2, AE5=5,AE5=6), SUM( FILTER( Income!$K$6:$K$8, AE4 >= Income!$M$6:$M$8 ) ) ,)"),0.0) -> 0 | AF18: =IFERROR(__xludf.DUMMYFUNCTION("IF( OR(AF5=1, AF5=2, AF5=5,AF5=6), SUM( FILTER( Income!$K$6:$K$8, AF4 >= Income!$M$6:$M$8 ) ) ,)"),0.0) -> 0 | AG18: =IFERROR(__xludf.DUMMYFUNCTION("IF( OR(AG5=1, AG5=2, AG5=5,AG5=6), SUM( FILTER( Income!$K$6:$K$8, AG4 >= Income!$M$6:$M$8 ) ) ,)"),0.0) -> 0 | AH18: =IFERROR(__xludf.DUMMYFUNCTION("IF( OR(AH5=1, AH5=2, AH5=5,AH5=6), SUM( FILTER( Income!$K$6:$K$8, AH4 >= Income!$M$6:$M$8 ) ) ,)"),0.0) -> 0 | AI18: =IFERROR(__xludf.DUMMYFUNCTION("IF( OR(AI5=1, AI5=2, AI5=5,AI5=6), SUM( FILTER( Income!$K$6:$K$8, AI4 >= Income!$M$6:$M$8 ) ) ,)"),0.0) -> 0 | AJ18: =IFERROR(__xludf.DUMMYFUNCTION("IF( OR(AJ5=1, AJ5=2, AJ5=5,AJ5=6), SUM( FILTER( Income!$K$6:$K$8, AJ4 >= Income!$M$6:$M$8 ) ) ,)"),0.0) -> 0 | AK18: =IFERROR(__xludf.DUMMYFUNCTION("IF( OR(AK5=1, AK5=2, AK5=5,AK5=6), SUM( FILTER( Income!$K$6:$K$8, AK4 >= Income!$M$6:$M$8 ) ) ,)"),0.0) -> 0 | AL18: =IFERROR(__xludf.DUMMYFUNCTION("IF( OR(AL5=1, AL5=2, AL5=5,AL5=6), SUM( FILTER( Income!$K$6:$K$8, AL4 >= Income!$M$6:$M$8 ) ) ,)"),"") | AM18: =IFERROR(__xludf.DUMMYFUNCTION("IF( OR(AM5=1, AM5=2, AM5=5,AM5=6), SUM( FILTER( Income!$K$6:$K$8, AM4 >= Income!$M$6:$M$8 ) ) ,)"),"") | AN18: =IFERROR(__xludf.DUMMYFUNCTION("IF( OR(AN5=1, AN5=2, AN5=5,AN5=6), SUM( FILTER( Income!$K$6:$K$8, AN4 >= Income!$M$6:$M$8 ) ) ,)"),"") | AO18: =IFERROR(__xludf.DUMMYFUNCTION("IF( OR(AO5=1, AO5=2, AO5=5,AO5=6), SUM( FILTER( Income!$K$6:$K$8, AO4 >= Income!$M$6:$M$8 ) ) ,)"),"") | AP18: =IFERROR(__xludf.DUMMYFUNCTION("IF( OR(AP5=1, AP5=2, AP5=5,AP5=6), SUM( FILTER( Income!$K$6:$K$8, AP4 >= Income!$M$6:$M$8 ) ) ,)"),"") | AQ18: =IFERROR(__xludf.DUMMYFUNCTION("IF( OR(AQ5=1, AQ5=2, AQ5=5,AQ5=6), SUM( FILTER( Income!$K$6:$K$8, AQ4 >= Income!$M$6:$M$8 ) ) ,)"),"") | AR18: =IFERROR(__xludf.DUMMYFUNCTION("IF( OR(AR5=1, AR5=2, AR5=5,AR5=6), SUM( FILTER( Income!$K$6:$K$8, AR4 >= Income!$M$6:$M$8 ) ) ,)"),"") | AS18: =IFERROR(__xludf.DUMMYFUNCTION("IF( OR(AS5=1, AS5=2, AS5=5,AS5=6), SUM( FILTER( Income!$K$6:$K$8, AS4 >= Income!$M$6:$M$8 ) ) ,)"),"") | AT18: =IFERROR(__xludf.DUMMYFUNCTION("IF( OR(AT5=1, AT5=2, AT5=5,AT5=6), SUM( FILTER( Income!$K$6:$K$8, AT4 >= Income!$M$6:$M$8 ) ) ,)"),"") | AU18: =IFERROR(__xludf.DUMMYFUNCTION("IF( OR(AU5=1, AU5=2, AU5=5,AU5=6), SUM( FILTER( Income!$K$6:$K$8, AU4 >= Income!$M$6:$M$8 ) ) ,)"),"") | AV18: =IFERROR(__xludf.DUMMYFUNCTION("IF( OR(AV5=1, AV5=2, AV5=5,AV5=6), SUM( FILTER( Income!$K$6:$K$8, AV4 >= Income!$M$6:$M$8 ) ) ,)"),"")
A19: Monthly Annuity | D19: =if(D18>0,D18/12,) | E19: =if(E18>0,E18/12,) | F19: =if(F18>0,F18/12,) | G19: =if(G18>0,G18/12,) | H19: =if(H18>0,H18/12,) | I19: =if(I18>0,I18/12,) | J19: =if(J18>0,J18/12,) | K19: =if(K18>0,K18/12,) | ... AV19: =if(AV18>0,AV18/12,)
A20: Annual DB Pensions | D20: =IFERROR(__xludf.DUMMYFUNCTION("IF( OR(D5=1,D5=2,D5=5,D5=6), SUM( FILTER( Income!$K$10:$K$12, D4 >= Income!$M$10:$M$12 ) ) ,)"),"") | E20: =IFERROR(__xludf.DUMMYFUNCTION("IF( OR(E5=1,E5=2,E5=5,E5=6), SUM( FILTER( Income!$K$10:$K$12, E4 >= Income!$M$10:$M$12 ) ) ,)"),"") | F20: =IFERROR(__xludf.DUMMYFUNCTION("IF( OR(F5=1,F5=2,F5=5,F5=6), SUM( FILTER( Income!$K$10:$K$12, F4 >= Income!$M$10:$M$12 ) ) ,)"),7000.0) -> 7000 | G20: =IFERROR(__xludf.DUMMYFUNCTION("IF( OR(G5=1,G5=2,G5=5,G5=6), SUM( FILTER( Income!$K$10:$K$12, G4 >= Income!$M$10:$M$12 ) ) ,)"),7000.0) -> 7000 | H20: =IFERROR(__xludf.DUMMYFUNCTION("IF( OR(H5=1,H5=2,H5=5,H5=6), SUM( FILTER( Income!$K$10:$K$12, H4 >= Income!$M$10:$M$12 ) ) ,)"),7000.0) -> 7000 | I20: =IFERROR(__xludf.DUMMYFUNCTION("IF( OR(I5=1,I5=2,I5=5,I5=6), SUM( FILTER( Income!$K$10:$K$12, I4 >= Income!$M$10:$M$12 ) ) ,)"),7000.0) -> 7000 | J20: =IFERROR(__xludf.DUMMYFUNCTION("IF( OR(J5=1,J5=2,J5=5,J5=6), SUM( FILTER( Income!$K$10:$K$12, J4 >= Income!$M$10:$M$12 ) ) ,)"),10000.0) -> 10000 | K20: =IFERROR(__xludf.DUMMYFUNCTION("IF( OR(K5=1,K5=2,K5=5,K5=6), SUM( FILTER( Income!$K$10:$K$12, K4 >= Income!$M$10:$M$12 ) ) ,)"),10000.0) -> 10000 | L20: =IFERROR(__xludf.DUMMYFUNCTION("IF( OR(L5=1,L5=2,L5=5,L5=6), SUM( FILTER( Income!$K$10:$K$12, L4 >= Income!$M$10:$M$12 ) ) ,)"),10000.0) -> 10000 | M20: =IFERROR(__xludf.DUMMYFUNCTION("IF( OR(M5=1,M5=2,M5=5,M5=6), SUM( FILTER( Income!$K$10:$K$12, M4 >= Income!$M$10:$M$12 ) ) ,)"),10000.0) -> 10000 | N20: =IFERROR(__xludf.DUMMYFUNCTION("IF( OR(N5=1,N5=2,N5=5,N5=6), SUM( FILTER( Income!$K$10:$K$12, N4 >= Income!$M$10:$M$12 ) ) ,)"),10000.0) -> 10000 | O20: =IFERROR(__xludf.DUMMYFUNCTION("IF( OR(O5=1,O5=2,O5=5,O5=6), SUM( FILTER( Income!$K$10:$K$12, O4 >= Income!$M$10:$M$12 ) ) ,)"),10000.0) -> 10000 | P20: =IFERROR(__xludf.DUMMYFUNCTION("IF( OR(P5=1,P5=2,P5=5,P5=6), SUM( FILTER( Income!$K$10:$K$12, P4 >= Income!$M$10:$M$12 ) ) ,)"),10000.0) -> 10000 | Q20: =IFERROR(__xludf.DUMMYFUNCTION("IF( OR(Q5=1,Q5=2,Q5=5,Q5=6), SUM( FILTER( Income!$K$10:$K$12, Q4 >= Income!$M$10:$M$12 ) ) ,)"),10000.0) -> 10000 | R20: =IFERROR(__xludf.DUMMYFUNCTION("IF( OR(R5=1,R5=2,R5=5,R5=6), SUM( FILTER( Income!$K$10:$K$12, R4 >= Income!$M$10:$M$12 ) ) ,)"),10000.0) -> 10000 | S20: =IFERROR(__xludf.DUMMYFUNCTION("IF( OR(S5=1,S5=2,S5=5,S5=6), SUM( FILTER( Income!$K$10:$K$12, S4 >= Income!$M$10:$M$12 ) ) ,)"),10000.0) -> 10000 | T20: =IFERROR(__xludf.DUMMYFUNCTION("IF( OR(T5=1,T5=2,T5=5,T5=6), SUM( FILTER( Income!$K$10:$K$12, T4 >= Income!$M$10:$M$12 ) ) ,)"),10000.0) -> 10000 | U20: =IFERROR(__xludf.DUMMYFUNCTION("IF( OR(U5=1,U5=2,U5=5,U5=6), SUM( FILTER( Income!$K$10:$K$12, U4 >= Income!$M$10:$M$12 ) ) ,)"),10000.0) -> 10000 | V20: =IFERROR(__xludf.DUMMYFUNCTION("IF( OR(V5=1,V5=2,V5=5,V5=6), SUM( FILTER( Income!$K$10:$K$12, V4 >= Income!$M$10:$M$12 ) ) ,)"),10000.0) -> 10000 | W20: =IFERROR(__xludf.DUMMYFUNCTION("IF( OR(W5=1,W5=2,W5=5,W5=6), SUM( FILTER( Income!$K$10:$K$12, W4 >= Income!$M$10:$M$12 ) ) ,)"),10000.0) -> 10000 | X20: =IFERROR(__xludf.DUMMYFUNCTION("IF( OR(X5=1,X5=2,X5=5,X5=6), SUM( FILTER( Income!$K$10:$K$12, X4 >= Income!$M$10:$M$12 ) ) ,)"),10000.0) -> 10000 | Y20: =IFERROR(__xludf.DUMMYFUNCTION("IF( OR(Y5=1,Y5=2,Y5=5,Y5=6), SUM( FILTER( Income!$K$10:$K$12, Y4 >= Income!$M$10:$M$12 ) ) ,)"),10000.0) -> 10000 | Z20: =IFERROR(__xludf.DUMMYFUNCTION("IF( OR(Z5=1,Z5=2,Z5=5,Z5=6), SUM( FILTER( Income!$K$10:$K$12, Z4 >= Income!$M$10:$M$12 ) ) ,)"),10000.0) -> 10000 | AA20: =IFERROR(__xludf.DUMMYFUNCTION("IF( OR(AA5=1,AA5=2,AA5=5,AA5=6), SUM( FILTER( Income!$K$10:$K$12, AA4 >= Income!$M$10:$M$12 ) ) ,)"),10000.0) -> 10000 | AB20: =IFERROR(__xludf.DUMMYFUNCTION("IF( OR(AB5=1,AB5=2,AB5=5,AB5=6), SUM( FILTER( Income!$K$10:$K$12, AB4 >= Income!$M$10:$M$12 ) ) ,)"),10000.0) -> 10000 | AC20: =IFERROR(__xludf.DUMMYFUNCTION("IF( OR(AC5=1,AC5=2,AC5=5,AC5=6), SUM( FILTER( Income!$K$10:$K$12, AC4 >= Income!$M$10:$M$12 ) ) ,)"),10000.0) -> 10000 | AD20: =IFERROR(__xludf.DUMMYFUNCTION("IF( OR(AD5=1,AD5=2,AD5=5,AD5=6), SUM( FILTER( Income!$K$10:$K$12, AD4 >= Income!$M$10:$M$12 ) ) ,)"),10000.0) -> 10000 | AE20: =IFERROR(__xludf.DUMMYFUNCTION("IF( OR(AE5=1,AE5=2,AE5=5,AE5=6), SUM( FILTER( Income!$K$10:$K$12, AE4 >= Income!$M$10:$M$12 ) ) ,)"),10000.0) -> 10000 | AF20: =IFERROR(__xludf.DUMMYFUNCTION("IF( OR(AF5=1,AF5=2,AF5=5,AF5=6), SUM( FILTER( Income!$K$10:$K$12, AF4 >= Income!$M$10:$M$12 ) ) ,)"),10000.0) -> 10000 | AG20: =IFERROR(__xludf.DUMMYFUNCTION("IF( OR(AG5=1,AG5=2,AG5=5,AG5=6), SUM( FILTER( Income!$K$10:$K$12, AG4 >= Income!$M$10:$M$12 ) ) ,)"),10000.0) -> 10000 | AH20: =IFERROR(__xludf.DUMMYFUNCTION("IF( OR(AH5=1,AH5=2,AH5=5,AH5=6), SUM( FILTER( Income!$K$10:$K$12, AH4 >= Income!$M$10:$M$12 ) ) ,)"),10000.0) -> 10000 | AI20: =IFERROR(__xludf.DUMMYFUNCTION("IF( OR(AI5=1,AI5=2,AI5=5,AI5=6), SUM( FILTER( Income!$K$10:$K$12, AI4 >= Income!$M$10:$M$12 ) ) ,)"),10000.0) -> 10000 | AJ20: =IFERROR(__xludf.DUMMYFUNCTION("IF( OR(AJ5=1,AJ5=2,AJ5=5,AJ5=6), SUM( FILTER( Income!$K$10:$K$12, AJ4 >= Income!$M$10:$M$12 ) ) ,)"),10000.0) -> 10000 | AK20: =IFERROR(__xludf.DUMMYFUNCTION("IF( OR(AK5=1,AK5=2,AK5=5,AK5=6), SUM( FILTER( Income!$K$10:$K$12, AK4 >= Income!$M$10:$M$12 ) ) ,)"),10000.0) -> 10000 | AL20: =IFERROR(__xludf.DUMMYFUNCTION("IF( OR(AL5=1,AL5=2,AL5=5,AL5=6), SUM( FILTER( Income!$K$10:$K$12, AL4 >= Income!$M$10:$M$12 ) ) ,)"),"") | AM20: =IFERROR(__xludf.DUMMYFUNCTION("IF( OR(AM5=1,AM5=2,AM5=5,AM5=6), SUM( FILTER( Income!$K$10:$K$12, AM4 >= Income!$M$10:$M$12 ) ) ,)"),"") | AN20: =IFERROR(__xludf.DUMMYFUNCTION("IF( OR(AN5=1,AN5=2,AN5=5,AN5=6), SUM( FILTER( Income!$K$10:$K$12, AN4 >= Income!$M$10:$M$12 ) ) ,)"),"") | AO20: =IFERROR(__xludf.DUMMYFUNCTION("IF( OR(AO5=1,AO5=2,AO5=5,AO5=6), SUM( FILTER( Income!$K$10:$K$12, AO4 >= Income!$M$10:$M$12 ) ) ,)"),"") | AP20: =IFERROR(__xludf.DUMMYFUNCTION("IF( OR(AP5=1,AP5=2,AP5=5,AP5=6), SUM( FILTER( Income!$K$10:$K$12, AP4 >= Income!$M$10:$M$12 ) ) ,)"),"") | AQ20: =IFERROR(__xludf.DUMMYFUNCTION("IF( OR(AQ5=1,AQ5=2,AQ5=5,AQ5=6), SUM( FILTER( Income!$K$10:$K$12, AQ4 >= Income!$M$10:$M$12 ) ) ,)"),"") | AR20: =IFERROR(__xludf.DUMMYFUNCTION("IF( OR(AR5=1,AR5=2,AR5=5,AR5=6), SUM( FILTER( Income!$K$10:$K$12, AR4 >= Income!$M$10:$M$12 ) ) ,)"),"") | AS20: =IFERROR(__xludf.DUMMYFUNCTION("IF( OR(AS5=1,AS5=2,AS5=5,AS5=6), SUM( FILTER( Income!$K$10:$K$12, AS4 >= Income!$M$10:$M$12 ) ) ,)"),"") | AT20: =IFERROR(__xludf.DUMMYFUNCTION("IF( OR(AT5=1,AT5=2,AT5=5,AT5=6), SUM( FILTER( Income!$K$10:$K$12, AT4 >= Income!$M$10:$M$12 ) ) ,)"),"") | AU20: =IFERROR(__xludf.DUMMYFUNCTION("IF( OR(AU5=1,AU5=2,AU5=5,AU5=6), SUM( FILTER( Income!$K$10:$K$12, AU4 >= Income!$M$10:$M$12 ) ) ,)"),"") | AV20: =IFERROR(__xludf.DUMMYFUNCTION("IF( OR(AV5=1,AV5=2,AV5=5,AV5=6), SUM( FILTER( Income!$K$10:$K$12, AV4 >= Income!$M$10:$M$12 ) ) ,)"),"")
A21: Monthly DB Pension | D21: =if(D20>0,D20/12,) | E21: =if(E20>0,E20/12,) | F21: =if(F20>0,F20/12,) -> 583.33333 | G21: =if(G20>0,G20/12,) -> 583.33333 | H21: =if(H20>0,H20/12,) -> 583.33333 | I21: =if(I20>0,I20/12,) -> 583.33333 | J21: =if(J20>0,J20/12,) -> 833.33333 | K21: =if(K20>0,K20/12,) -> 833.33333 | ... AV21: =if(AV20>0,AV20/12,)
A22: Annual Cash | D22: =IF( OR(D5=1,D5=2,D5=5,D5=6),Income!$M$16 ,) | E22: =IF( OR(E5=1,E5=2,E5=5,E5=6),Income!$M$16 ,) | F22: =IF( OR(F5=1,F5=2,F5=5,F5=6),Income!$M$16 ,) -> 4837.49 | G22: =IF( OR(G5=1,G5=2,G5=5,G5=6),Income!$M$16 ,) -> 4837.49 | H22: =IF( OR(H5=1,H5=2,H5=5,H5=6),Income!$M$16 ,) -> 4837.49 | I22: =IF( OR(I5=1,I5=2,I5=5,I5=6),Income!$M$16 ,) -> 4837.49 | J22: =IF( OR(J5=1,J5=2,J5=5,J5=6),Income!$M$16 ,) -> 4837.49 | K22: =IF( OR(K5=1,K5=2,K5=5,K5=6),Income!$M$16 ,) -> 4837.49 | ... AV22: =IF( OR(AV5=1,AV5=2,AV5=5,AV5=6),Income!$M$16 ,)
A23: Monthly Cash | D23: =if(D22>0, D22 / 12,) | E23: =if(E22>0, E22 / 12,) | F23: =if(F22>0, F22 / 12,) -> 403.12417 | G23: =if(G22>0, G22 / 12,) -> 403.12417 | H23: =if(H22>0, H22 / 12,) -> 403.12417 | I23: =if(I22>0, I22 / 12,) -> 403.12417 | J23: =if(J22>0, J22 / 12,) -> 403.12417 | K23: =if(K22>0, K22 / 12,) -> 403.12417 | ... AV23: =if(AV22>0, AV22 / 12,)
A24: Total Annual Income | D24: =IF( OR(D5 = 0, D5 = 3, D5 = 4, D5 = 7), "", IF( D5 = 1, 'Person 2 Calculator'!$F$9, IF( OR(D5 = 2, D5 = 5, D5 = 6), D7 + D12 + D14 + D16 + D18 + D20 + D22, "" ) ) ) | E24: =IF( OR(E5 = 0, E5 = 3, E5 = 4, E5 = 7), "", IF( E5 = 1, 'Person 2 Calculator'!$F$9, IF( OR(E5 = 2, E5 = 5, E5 = 6), E7 + E12 + E14 + E16 + E18 + E20 + E22, "" ) ) ) | F24: =IF( OR(F5 = 0, F5 = 3, F5 = 4, F5 = 7), "", IF( F5 = 1, 'Person 2 Calculator'!$F$9, IF( OR(F5 = 2, F5 = 5, F5 = 6), F7 + F12 + F14 + F16 + F18 + F20 + F22, "" ) ) ) -> 18924.1 | G24: =IF( OR(G5 = 0, G5 = 3, G5 = 4, G5 = 7), "", IF( G5 = 1, 'Person 2 Calculator'!$F$9, IF( OR(G5 = 2, G5 = 5, G5 = 6), G7 + G12 + G14 + G16 + G18 + G20 + G22, "" ) ) ) -> 18924.1 | H24: =IF( OR(H5 = 0, H5 = 3, H5 = 4, H5 = 7), "", IF( H5 = 1, 'Person 2 Calculator'!$F$9, IF( OR(H5 = 2, H5 = 5, H5 = 6), H7 + H12 + H14 + H16 + H18 + H20 + H22, "" ) ) ) -> 18924.1 | I24: =IF( OR(I5 = 0, I5 = 3, I5 = 4, I5 = 7), "", IF( I5 = 1, 'Person 2 Calculator'!$F$9, IF( OR(I5 = 2, I5 = 5, I5 = 6), I7 + I12 + I14 + I16 + I18 + I20 + I22, "" ) ) ) -> 18924.1 | J24: =IF( OR(J5 = 0, J5 = 3, J5 = 4, J5 = 7), "", IF( J5 = 1, 'Person 2 Calculator'!$F$9, IF( OR(J5 = 2, J5 = 5, J5 = 6), J7 + J12 + J14 + J16 + J18 + J20 + J22, "" ) ) ) -> 21924.1 | K24: =IF( OR(K5 = 0, K5 = 3, K5 = 4, K5 = 7), "", IF( K5 = 1, 'Person 2 Calculator'!$F$9, IF( OR(K5 = 2, K5 = 5, K5 = 6), K7 + K12 + K14 + K16 + K18 + K20 + K22, "" ) ) ) -> 21924.1 | ... AV24: =IF( OR(AV5 = 0, AV5 = 3, AV5 = 4, AV5 = 7), "", IF( AV5 = 1, 'Person 2 Calculator'!$F$9, IF( OR(AV5 = 2, AV5 = 5, AV5 = 6), AV7 + AV12 + AV14 + AV16 + AV18 + AV20 + AV22, "" ) ) )
A25: Total Monthly Income | D25: =if(n(D24)>0,D24/12,) | E25: =if(n(E24)>0,E24/12,) | F25: =if(n(F24)>0,F24/12,) -> 1577.0083 | G25: =if(n(G24)>0,G24/12,) -> 1577.0083 | H25: =if(n(H24)>0,H24/12,) -> 1577.0083 | I25: =if(n(I24)>0,I24/12,) -> 1577.0083 | J25: =if(n(J24)>0,J24/12,) -> 1827.0083 | K25: =if(n(K24)>0,K24/12,) -> 1827.0083 | ... AV25: =if(n(AV24)>0,AV24/12,)
A26: =concatenate("Target income with inflation of ",text('Person 1 Calculator'!F18,"0.0%")) -> Target income with inflation of 2.5% | D26: =if(D5=0,, if( D5=1, D24,if(D5=5, D24,if(OR(D5=2,D5=6),C26*(1+'Person 2 Calculator'!$F$18),if(OR(D5=3,D5=4,D5=7),))))) | E26: =if(E5=0,, if( E5=1, E24,if(E5=5, E24,if(OR(E5=2,E5=6),D26*(1+'Person 2 Calculator'!$F$18),if(OR(E5=3,E5=4,E5=7),))))) | F26: =if(F5=0,, if( F5=1, F24,if(F5=5, F24,if(OR(F5=2,F5=6),E26*(1+'Person 2 Calculator'!$F$18),if(OR(F5=3,F5=4,F5=7),))))) -> 18924.1 | G26: =if(G5=0,, if( G5=1, G24,if(G5=5, G24,if(OR(G5=2,G5=6),F26*(1+'Person 2 Calculator'!$F$18),if(OR(G5=3,G5=4,G5=7),))))) -> 19397.202 | H26: =if(H5=0,, if( H5=1, H24,if(H5=5, H24,if(OR(H5=2,H5=6),G26*(1+'Person 2 Calculator'!$F$18),if(OR(H5=3,H5=4,H5=7),))))) -> 19882.133 | I26: =if(I5=0,, if( I5=1, I24,if(I5=5, I24,if(OR(I5=2,I5=6),H26*(1+'Person 2 Calculator'!$F$18),if(OR(I5=3,I5=4,I5=7),))))) -> 20379.186 | J26: =if(J5=0,, if( J5=1, J24,if(J5=5, J24,if(OR(J5=2,J5=6),I26*(1+'Person 2 Calculator'!$F$18),if(OR(J5=3,J5=4,J5=7),))))) -> 20888.666 | K26: =if(K5=0,, if( K5=1, K24,if(K5=5, K24,if(OR(K5=2,K5=6),J26*(1+'Person 2 Calculator'!$F$18),if(OR(K5=3,K5=4,K5=7),))))) -> 21410.882 | ... AV26: =if(AV5=0,, if( AV5=1, AV24,if(AV5=5, AV24,if(OR(AV5=2,AV5=6),AU26*(1+'Person 2 Calculator'!$F$18),if(OR(AV5=3,AV5=4,AV5=7),)))))
A27: Performance against inflation | D27: =if(AND(D24>0, D26>0),D24/D26,) | E27: =if(AND(E24>0, E26>0),E24/E26,) | F27: =if(AND(F24>0, F26>0),F24/F26,) -> 1 | G27: =if(AND(G24>0, G26>0),G24/G26,) -> 0.97560976 | H27: =if(AND(H24>0, H26>0),H24/H26,) -> 0.9518144 | I27: =if(AND(I24>0, I26>0),I24/I26,) -> 0.92859941 | J27: =if(AND(J24>0, J26>0),J24/J26,) -> 1.0495692 | K27: =if(AND(K24>0, K26>0),K24/K26,) -> 1.02397 | ... AV27: =if(AND(AV24>0, AV26>0),AV24/AV26,)
A28: Annual SIPP Draw-down Rate | D28: =if(D6>D7,D7/D6,) | E28: =if(E6>E7,E7/E6,) | F28: =if(F6>F7,F7/F6,) | G28: =if(G6>G7,G7/G6,) | H28: =if(H6>H7,H7/H6,) | I28: =if(I6>I7,I7/I6,) | J28: =if(J6>J7,J7/J6,) | K28: =if(K6>K7,K7/K6,) | ... AV28: =if(AV6>AV7,AV7/AV6,)
A29: Taxable income | D29: =if(D24=0,,(if(AND(D24>0,D10<268275), D8+D14+D16+D18+D20+D22,if(D10>268275,D8+D9+D14+D16+D18+D20+D22)))) -> 0 | E29: =if(E24=0,,(if(AND(E24>0,E10<268275), E8+E14+E16+E18+E20+E22,if(E10>268275,E8+E9+E14+E16+E18+E20+E22)))) -> 0 | F29: =if(F24=0,,(if(AND(F24>0,F10<268275), F8+F14+F16+F18+F20+F22,if(F10>268275,F8+F9+F14+F16+F18+F20+F22)))) -> 11837.49 | G29: =if(G24=0,,(if(AND(G24>0,G10<268275), G8+G14+G16+G18+G20+G22,if(G10>268275,G8+G9+G14+G16+G18+G20+G22)))) -> 11837.49 | H29: =if(H24=0,,(if(AND(H24>0,H10<268275), H8+H14+H16+H18+H20+H22,if(H10>268275,H8+H9+H14+H16+H18+H20+H22)))) -> 11837.49 | I29: =if(I24=0,,(if(AND(I24>0,I10<268275), I8+I14+I16+I18+I20+I22,if(I10>268275,I8+I9+I14+I16+I18+I20+I22)))) -> 11837.49 | J29: =if(J24=0,,(if(AND(J24>0,J10<268275), J8+J14+J16+J18+J20+J22,if(J10>268275,J8+J9+J14+J16+J18+J20+J22)))) -> 14837.49 | K29: =if(K24=0,,(if(AND(K24>0,K10<268275), K8+K14+K16+K18+K20+K22,if(K10>268275,K8+K9+K14+K16+K18+K20+K22)))) -> 14837.49 | ... AV29: =if(AV24=0,,(if(AND(AV24>0,AV10<268275), AV8+AV14+AV16+AV18+AV20+AV22,if(AV10>268275,AV8+AV9+AV14+AV16+AV18+AV20+AV22)))) -> 0
A30: Tax | D30: =LET( Income, D29, PA_Limit, 12570, BR_Limit, 50270, HR_Limit, 125140, Taper_Start, 100000, Tapered_PA, MAX(0, PA_Limit - MAX(0, (Income - Taper_Start) / 2)), TaxableIncome, MAX(0, Income - Tapered_PA), BasicRateTax, MAX(0, MIN(TaxableIncome, BR_Limit - PA_Limit)) * 0.2, HigherRateBandWidth, HR_Limit - BR_Limit, HigherRateTax, MAX(0, MIN(TaxableIncome - (BR_Limit - PA_Limit), HigherRateBandWidth)) * 0.4, AdditionalRateTax, MAX(0, TaxableIncome - (HR_Limit - PA_Limit)) * 0.45, TotalTax, BasicRateTax + HigherRateTax + AdditionalRateTax, IF(OR(ISBLANK(Income), Income = 0), "", TotalTax) ) | E30: =LET( Income, E29, PA_Limit, 12570, BR_Limit, 50270, HR_Limit, 125140, Taper_Start, 100000, Tapered_PA, MAX(0, PA_Limit - MAX(0, (Income - Taper_Start) / 2)), TaxableIncome, MAX(0, Income - Tapered_PA), BasicRateTax, MAX(0, MIN(TaxableIncome, BR_Limit - PA_Limit)) * 0.2, HigherRateBandWidth, HR_Limit - BR_Limit, HigherRateTax, MAX(0, MIN(TaxableIncome - (BR_Limit - PA_Limit), HigherRateBandWidth)) * 0.4, AdditionalRateTax, MAX(0, TaxableIncome - (HR_Limit - PA_Limit)) * 0.45, TotalTax, BasicRateTax + HigherRateTax + AdditionalRateTax, IF(OR(ISBLANK(Income), Income = 0), "", TotalTax) ) | F30: =LET( Income, F29, PA_Limit, 12570, BR_Limit, 50270, HR_Limit, 125140, Taper_Start, 100000, Tapered_PA, MAX(0, PA_Limit - MAX(0, (Income - Taper_Start) / 2)), TaxableIncome, MAX(0, Income - Tapered_PA), BasicRateTax, MAX(0, MIN(TaxableIncome, BR_Limit - PA_Limit)) * 0.2, HigherRateBandWidth, HR_Limit - BR_Limit, HigherRateTax, MAX(0, MIN(TaxableIncome - (BR_Limit - PA_Limit), HigherRateBandWidth)) * 0.4, AdditionalRateTax, MAX(0, TaxableIncome - (HR_Limit - PA_Limit)) * 0.45, TotalTax, BasicRateTax + HigherRateTax + AdditionalRateTax, IF(OR(ISBLANK(Income), Income = 0), "", TotalTax) ) -> 0 | G30: =LET( Income, G29, PA_Limit, 12570, BR_Limit, 50270, HR_Limit, 125140, Taper_Start, 100000, Tapered_PA, MAX(0, PA_Limit - MAX(0, (Income - Taper_Start) / 2)), TaxableIncome, MAX(0, Income - Tapered_PA), BasicRateTax, MAX(0, MIN(TaxableIncome, BR_Limit - PA_Limit)) * 0.2, HigherRateBandWidth, HR_Limit - BR_Limit, HigherRateTax, MAX(0, MIN(TaxableIncome - (BR_Limit - PA_Limit), HigherRateBandWidth)) * 0.4, AdditionalRateTax, MAX(0, TaxableIncome - (HR_Limit - PA_Limit)) * 0.45, TotalTax, BasicRateTax + HigherRateTax + AdditionalRateTax, IF(OR(ISBLANK(Income), Income = 0), "", TotalTax) ) -> 0 | H30: =LET( Income, H29, PA_Limit, 12570, BR_Limit, 50270, HR_Limit, 125140, Taper_Start, 100000, Tapered_PA, MAX(0, PA_Limit - MAX(0, (Income - Taper_Start) / 2)), TaxableIncome, MAX(0, Income - Tapered_PA), BasicRateTax, MAX(0, MIN(TaxableIncome, BR_Limit - PA_Limit)) * 0.2, HigherRateBandWidth, HR_Limit - BR_Limit, HigherRateTax, MAX(0, MIN(TaxableIncome - (BR_Limit - PA_Limit), HigherRateBandWidth)) * 0.4, AdditionalRateTax, MAX(0, TaxableIncome - (HR_Limit - PA_Limit)) * 0.45, TotalTax, BasicRateTax + HigherRateTax + AdditionalRateTax, IF(OR(ISBLANK(Income), Income = 0), "", TotalTax) ) -> 0 | I30: =LET( Income, I29, PA_Limit, 12570, BR_Limit, 50270, HR_Limit, 125140, Taper_Start, 100000, Tapered_PA, MAX(0, PA_Limit - MAX(0, (Income - Taper_Start) / 2)), TaxableIncome, MAX(0, Income - Tapered_PA), BasicRateTax, MAX(0, MIN(TaxableIncome, BR_Limit - PA_Limit)) * 0.2, HigherRateBandWidth, HR_Limit - BR_Limit, HigherRateTax, MAX(0, MIN(TaxableIncome - (BR_Limit - PA_Limit), HigherRateBandWidth)) * 0.4, AdditionalRateTax, MAX(0, TaxableIncome - (HR_Limit - PA_Limit)) * 0.45, TotalTax, BasicRateTax + HigherRateTax + AdditionalRateTax, IF(OR(ISBLANK(Income), Income = 0), "", TotalTax) ) -> 0 | J30: =LET( Income, J29, PA_Limit, 12570, BR_Limit, 50270, HR_Limit, 125140, Taper_Start, 100000, Tapered_PA, MAX(0, PA_Limit - MAX(0, (Income - Taper_Start) / 2)), TaxableIncome, MAX(0, Income - Tapered_PA), BasicRateTax, MAX(0, MIN(TaxableIncome, BR_Limit - PA_Limit)) * 0.2, HigherRateBandWidth, HR_Limit - BR_Limit, HigherRateTax, MAX(0, MIN(TaxableIncome - (BR_Limit - PA_Limit), HigherRateBandWidth)) * 0.4, AdditionalRateTax, MAX(0, TaxableIncome - (HR_Limit - PA_Limit)) * 0.45, TotalTax, BasicRateTax + HigherRateTax + AdditionalRateTax, IF(OR(ISBLANK(Income), Income = 0), "", TotalTax) ) -> 453.498 | K30: =LET( Income, K29, PA_Limit, 12570, BR_Limit, 50270, HR_Limit, 125140, Taper_Start, 100000, Tapered_PA, MAX(0, PA_Limit - MAX(0, (Income - Taper_Start) / 2)), TaxableIncome, MAX(0, Income - Tapered_PA), BasicRateTax, MAX(0, MIN(TaxableIncome, BR_Limit - PA_Limit)) * 0.2, HigherRateBandWidth, HR_Limit - BR_Limit, HigherRateTax, MAX(0, MIN(TaxableIncome - (BR_Limit - PA_Limit), HigherRateBandWidth)) * 0.4, AdditionalRateTax, MAX(0, TaxableIncome - (HR_Limit - PA_Limit)) * 0.45, TotalTax, BasicRateTax + HigherRateTax + AdditionalRateTax, IF(OR(ISBLANK(Income), Income = 0), "", TotalTax) ) -> 453.498 | ... AV30: =LET( Income, AV29, PA_Limit, 12570, BR_Limit, 50270, HR_Limit, 125140, Taper_Start, 100000, Tapered_PA, MAX(0, PA_Limit - MAX(0, (Income - Taper_Start) / 2)), TaxableIncome, MAX(0, Income - Tapered_PA), BasicRateTax, MAX(0, MIN(TaxableIncome, BR_Limit - PA_Limit)) * 0.2, HigherRateBandWidth, HR_Limit - BR_Limit, HigherRateTax, MAX(0, MIN(TaxableIncome - (BR_Limit - PA_Limit), HigherRateBandWidth)) * 0.4, AdditionalRateTax, MAX(0, TaxableIncome - (HR_Limit - PA_Limit)) * 0.45, TotalTax, BasicRateTax + HigherRateTax + AdditionalRateTax, IF(OR(ISBLANK(Income), Income = 0), "", TotalTax) )
A31: Effective tax rate | D31: =if(AND(n(D30)>0, D24>0),D30/D24,) | E31: =if(AND(n(E30)>0, E24>0),E30/E24,) | F31: =if(AND(n(F30)>0, F24>0),F30/F24,) | G31: =if(AND(n(G30)>0, G24>0),G30/G24,) | H31: =if(AND(n(H30)>0, H24>0),H30/H24,) | I31: =if(AND(n(I30)>0, I24>0),I30/I24,) | J31: =if(AND(n(J30)>0, J24>0),J30/J24,) -> 0.020684908 | K31: =if(AND(n(K30)>0, K24>0),K30/K24,) -> 0.020684908 | ... AV31: =if(AND(n(AV30)>0, AV24>0),AV30/AV24,)
A32: Total Net Income | D32: =if(n(D24)>0,D24-D30,) | E32: =if(n(E24)>0,E24-E30,) | F32: =if(n(F24)>0,F24-F30,) -> 18924.1 | G32: =if(n(G24)>0,G24-G30,) -> 18924.1 | H32: =if(n(H24)>0,H24-H30,) -> 18924.1 | I32: =if(n(I24)>0,I24-I30,) -> 18924.1 | J32: =if(n(J24)>0,J24-J30,) -> 21470.602 | K32: =if(n(K24)>0,K24-K30,) -> 21470.602 | ... AV32: =if(n(AV24)>0,AV24-AV30,)
A33: Net Income Monthly | D33: =if(D32>0,D32/12,) | E33: =if(E32>0,E32/12,) | F33: =if(F32>0,F32/12,) -> 1577.0083 | G33: =if(G32>0,G32/12,) -> 1577.0083 | H33: =if(H32>0,H32/12,) -> 1577.0083 | I33: =if(I32>0,I32/12,) -> 1577.0083 | J33: =if(J32>0,J32/12,) -> 1789.2168 | K33: =if(K32>0,K32/12,) -> 1789.2168 | ... AV33: =if(AV32>0,AV32/12,)
A34: NPV | D34: =if(OR(D5=1,D5=2,D5=5,D5=6),D27*'Person 2 Calculator'!$F$9,) | E34: =if(OR(E5=1,E5=2,E5=5,E5=6),E27*'Person 2 Calculator'!$F$9,) | F34: =if(OR(F5=1,F5=2,F5=5,F5=6),F27*'Person 2 Calculator'!$F$9,) -> 18924.1 | G34: =if(OR(G5=1,G5=2,G5=5,G5=6),G27*'Person 2 Calculator'!$F$9,) -> 18462.537 | H34: =if(OR(H5=1,H5=2,H5=5,H5=6),H27*'Person 2 Calculator'!$F$9,) -> 18012.231 | I34: =if(OR(I5=1,I5=2,I5=5,I5=6),I27*'Person 2 Calculator'!$F$9,) -> 17572.908 | J34: =if(OR(J5=1,J5=2,J5=5,J5=6),J27*'Person 2 Calculator'!$F$9,) -> 19862.153 | K34: =if(OR(K5=1,K5=2,K5=5,K5=6),K27*'Person 2 Calculator'!$F$9,) -> 19377.71 | ... AV34: =if(OR(AV5=1,AV5=2,AV5=5,AV5=6),AV27*'Person 2 Calculator'!$F$9,)
A35: Net NPV | D35: =if(OR(D5=1,D5=2,D5=5,D5=6),D27*'Person 2 Calculator'!$D$9,) | E35: =if(OR(E5=1,E5=2,E5=5,E5=6),E27*'Person 2 Calculator'!$D$9,) | F35: =if(OR(F5=1,F5=2,F5=5,F5=6),F27*'Person 2 Calculator'!$D$9,) -> 18924.1 | G35: =if(OR(G5=1,G5=2,G5=5,G5=6),G27*'Person 2 Calculator'!$D$9,) -> 18462.537 | H35: =if(OR(H5=1,H5=2,H5=5,H5=6),H27*'Person 2 Calculator'!$D$9,) -> 18012.231 | I35: =if(OR(I5=1,I5=2,I5=5,I5=6),I27*'Person 2 Calculator'!$D$9,) -> 17572.908 | J35: =if(OR(J5=1,J5=2,J5=5,J5=6),J27*'Person 2 Calculator'!$D$9,) -> 19862.153 | K35: =if(OR(K5=1,K5=2,K5=5,K5=6),K27*'Person 2 Calculator'!$D$9,) -> 19377.71 | ... AV35: =if(OR(AV5=1,AV5=2,AV5=5,AV5=6),AV27*'Person 2 Calculator'!$D$9,)

Sheet Combined Pensions
V1: Combined Income
L2: First Year's combined income before tax | N2: ='Person 1 Calculator'!F9+'Person 2 Calculator'!F9 -> 127593.77
L3: First Year's combined income after tax | N3: ='Person 1 Calculator'!D9+'Person 2 Calculator'!D9 -> 108009.35
L4: First Year's tax | N4: =N2-N3 -> 19584.422
L6: Last Year's combined income net present amount | N6: ='Person 1 Calculator'!D12+'Person 2 Calculator'!D12 -> 82416.749
A9: Year | B9: 2005 | C9: =B9+1 -> 2006 | D9: =C9+1 -> 2007 | E9: =D9+1 -> 2008 | F9: =E9+1 -> 2009 | G9: =F9+1 -> 2010 | H9: =G9+1 -> 2011 | I9: =H9+1 -> 2012 | J9: =I9+1 -> 2013 | ... BT9: =BS9+1 -> 2075
A10: Person 1 Age | T10: 55 | U10: 56 | V10: 57 | W10: 58 | X10: 59 | Y10: 60 | Z10: 61 | AA10: 62 | AB10: 63 | AC10: 64 | AD10: 65 | AE10: 66 | AF10: 67 | AG10: 68 | AH10: 69 | AI10: 70 | AJ10: 71 | AK10: 72 | AL10: 73 | AM10: 74 | AN10: 75 | AO10: 76 | AP10: 77 | AQ10: 78 | AR10: 79 | AS10: 80 | AT10: 81 | AU10: 82 | AV10: 83 | AW10: 84 | AX10: 85 | AY10: 86 | AZ10: 87 | BA10: 88 | BB10: 89
A11: Person 2 Age | U11: 55 | V11: 56 | W11: 57 | X11: 58 | Y11: 59 | Z11: 60 | AA11: 61 | AB11: 62 | AC11: 63 | AD11: 64 | AE11: 65 | AF11: 66 | AG11: 67 | AH11: 68 | AI11: 69 | AJ11: 70 | AK11: 71 | AL11: 72 | AM11: 73 | AN11: 74 | AO11: 75 | AP11: 76 | AQ11: 77 | AR11: 78 | AS11: 79 | AT11: 80 | AU11: 81 | AV11: 82 | AW11: 83 | AX11: 84 | AY11: 85 | AZ11: 86 | BA11: 87 | BB11: 88
A12: INCOME PERFORMANCE
A13: Person 1 Net NPV | W13: 89085.252 | X13: 89085.252 | Y13: 89085.252 | Z13: 89085.252 | AA13: 89085.252 | AB13: 89085.252 | AC13: 89085.252 | AD13: 89085.252 | AE13: 89085.252 | AF13: 89085.252 | AG13: 89085.252 | AH13: 89085.252 | AI13: 71268.202 | AJ13: 71268.202 | AK13: 71268.202 | AL13: 71268.202 | AM13: 71268.202 | AN13: 71268.202 | AO13: 71268.202 | AP13: 71268.202 | AQ13: 71268.202 | AR13: 71268.202 | AS13: 53451.151 | AT13: 53451.151 | AU13: 53451.151 | AV13: 53451.151 | AW13: 53451.151 | AX13: 53451.151 | AY13: 53451.151 | AZ13: 53451.151 | BA13: 53451.151 | BB13: 53451.151
A14: Person 2 Net NPV | W14: 18924.1 | X14: 18462.537 | Y14: 18012.231 | Z14: 17572.908 | AA14: 19862.153 | AB14: 19377.71 | AC14: 18905.083 | AD14: 18443.983 | AE14: 17994.13 | AF14: 17555.249 | AG14: 30972.224 | AH14: 30757.102 | AI14: 30555.134 | AJ14: 30366.115 | AK14: 30189.846 | AL14: 30026.135 | AM14: 29874.797 | AN14: 29735.653 | AO14: 29608.529 | AP14: 29493.26 | AQ14: 29389.683 | AR14: 29297.643 | AS14: 29216.992 | AT14: 29147.585 | AU14: 29089.283 | AV14: 29041.954 | AW14: 29005.469 | AX14: 28979.706 | AY14: 28964.548 | AZ14: 28959.881 | BA14: 28965.598 | BB14: 28981.595
A15: Total Net NPV | V15: =if(OR(V13>0,V14>0),sum(V13:V14),) | W15: =if(OR(W13>0,W14>0),sum(W13:W14),) -> 108009.35 | X15: =if(OR(X13>0,X14>0),sum(X13:X14),) -> 107547.79 | Y15: =if(OR(Y13>0,Y14>0),sum(Y13:Y14),) -> 107097.48 | Z15: =if(OR(Z13>0,Z14>0),sum(Z13:Z14),) -> 106658.16 | AA15: =if(OR(AA13>0,AA14>0),sum(AA13:AA14),) -> 108947.4 | AB15: =if(OR(AB13>0,AB14>0),sum(AB13:AB14),) -> 108462.96 | AC15: =if(OR(AC13>0,AC14>0),sum(AC13:AC14),) -> 107990.34 | ... BT15: =if(OR(BT13>0,BT14>0),sum(BT13:BT14),)
A16: Person 1 Total Annual Income | W16: 108669.67 | X16: 111386.42 | Y16: 114171.08 | Z16: 117025.35 | AA16: 119950.99 | AB16: 122949.76 | AC16: 126023.51 | AD16: 129174.09 | AE16: 132403.45 | AF16: 135713.53 | AG16: 139106.37 | AH16: 142584.03 | AI16: 116918.91 | AJ16: 119841.88 | AK16: 122837.92 | AL16: 125908.87 | AM16: 129056.59 | AN16: 132283.01 | AO16: 135590.08 | AP16: 138979.84 | AQ16: 142454.33 | AR16: 146015.69 | AS16: 112249.56 | AT16: 115055.8 | AU16: 117932.2 | AV16: 120880.5 | AW16: 123902.51 | AX16: 127000.08 | AY16: 130175.08 | AZ16: 133429.46 | BA16: 136765.19 | BB16: 140184.32
A17: Person 2 Total Annual Income | W17: 18924.1 | X17: 18924.1 | Y17: 18924.1 | Z17: 18924.1 | AA17: 21924.1 | AB17: 21924.1 | AC17: 21924.1 | AD17: 21924.1 | AE17: 21924.1 | AF17: 21924.1 | AG17: 39647.065 | AH17: 40355.983 | AI17: 41093.259 | AJ17: 41860.025 | AK17: 42657.462 | AL17: 43486.797 | AM17: 44349.304 | AN17: 45246.313 | AO17: 46179.201 | AP17: 47149.405 | AQ17: 48158.417 | AR17: 49207.79 | AS17: 50299.138 | AT17: 51434.139 | AU17: 52614.541 | AV17: 53842.158 | AW17: 55118.881 | AX17: 56446.672 | AY17: 57827.575 | AZ17: 59263.714 | BA17: 60757.298 | BB17: 62310.626
A18: Total Income | V18: =if(OR(V16>0,V17>0),sum(V16:V17),) | W18: =if(OR(W16>0,W17>0),sum(W16:W17),) -> 127593.77 | X18: =if(OR(X16>0,X17>0),sum(X16:X17),) -> 130310.52 | Y18: =if(OR(Y16>0,Y17>0),sum(Y16:Y17),) -> 133095.18 | Z18: =if(OR(Z16>0,Z17>0),sum(Z16:Z17),) -> 135949.45 | AA18: =if(OR(AA16>0,AA17>0),sum(AA16:AA17),) -> 141875.09 | AB18: =if(OR(AB16>0,AB17>0),sum(AB16:AB17),) -> 144873.86 | AC18: =if(OR(AC16>0,AC17>0),sum(AC16:AC17),) -> 147947.61 | ... BT18: =if(OR(BT16>0,BT17>0),sum(BT16:BT17),)
A19: Person 1 Tax | W19: 19584.422 | X19: 20449.445 | Y19: 21336.093 | Z19: 22244.907 | AA19: 23176.442 | AB19: 24131.265 | AC19: 25109.959 | AD19: 26113.12 | AE19: 27141.36 | AF19: 29967.602 | AG19: 31118.789 | AH19: 32299.818 | AI19: 30719.922 | AJ19: 31889.111 | AK19: 33087.53 | AL19: 34315.909 | AM19: 35574.998 | AN19: 36865.564 | AO19: 38275.943 | AP19: 39801.332 | AQ19: 41364.855 | AR19: 42967.466 | AS19: 28852.185 | AT19: 29974.681 | AU19: 31125.239 | AV19: 32304.561 | AW19: 33513.366 | AX19: 34752.391 | AY19: 36022.391 | AZ19: 37324.142 | BA19: 38804.741 | BB19: 40343.35
A20: Person 2 Tax | AA20: 453.498 | AB20: 453.498 | AC20: 453.498 | AD20: 453.498 | AE20: 453.498 | AF20: 453.498 | AG20: 3998.091 | AH20: 4139.8747 | AI20: 4287.3298 | AJ20: 4440.683 | AK20: 4600.1704 | AL20: 4766.0373 | AM20: 4938.5389 | AN20: 5117.9405 | AO20: 5304.5182 | AP20: 5498.559 | AQ20: 5700.3615 | AR20: 5910.236 | AS20: 6128.5055 | AT20: 6355.5058 | AU20: 6591.5862 | AV20: 6837.1097 | AW20: 7092.4541 | AX20: 7358.0124 | AY20: 7728.3859 | AZ20: 8302.8415 | BA20: 8900.2754 | BB20: 9521.6065
A21: Total Tax | V21: =if(OR(V19>0,V20>0),sum(V19:V20),) | W21: =if(OR(W19>0,W20>0),sum(W19:W20),) -> 19584.422 | X21: =if(OR(X19>0,X20>0),sum(X19:X20),) -> 20449.445 | Y21: =if(OR(Y19>0,Y20>0),sum(Y19:Y20),) -> 21336.093 | Z21: =if(OR(Z19>0,Z20>0),sum(Z19:Z20),) -> 22244.907 | AA21: =if(OR(AA19>0,AA20>0),sum(AA19:AA20),) -> 23629.94 | AB21: =if(OR(AB19>0,AB20>0),sum(AB19:AB20),) -> 24584.763 | AC21: =if(OR(AC19>0,AC20>0),sum(AC19:AC20),) -> 25563.457 | ... BT21: =if(OR(BT19>0,BT20>0),sum(BT19:BT20),)
A22: Person 1 Net Income | W22: 89085.252 | X22: 90936.972 | Y22: 92834.984 | Z22: 94780.447 | AA22: 96774.546 | AB22: 98818.497 | AC22: 100913.55 | AD22: 103060.97 | AE22: 105262.09 | AF22: 105745.93 | AG22: 107987.58 | AH22: 110284.21 | AI22: 86198.983 | AJ22: 87952.767 | AK22: 89750.395 | AL22: 91592.964 | AM22: 93481.597 | AN22: 95417.446 | AO22: 97314.142 | AP22: 99178.505 | AQ22: 101089.48 | AR22: 103048.23 | AS22: 83397.377 | AT22: 85081.121 | AU22: 86806.958 | AV22: 88575.941 | AW22: 90389.148 | AX22: 92247.686 | AY22: 94152.687 | AZ22: 96105.313 | BA22: 97960.451 | BB22: 99840.972
A23: Person 2 Net Income | W23: 18924.1 | X23: 18924.1 | Y23: 18924.1 | Z23: 18924.1 | AA23: 21470.602 | AB23: 21470.602 | AC23: 21470.602 | AD23: 21470.602 | AE23: 21470.602 | AF23: 21470.602 | AG23: 35648.974 | AH23: 36216.109 | AI23: 36805.929 | AJ23: 37419.342 | AK23: 38057.292 | AL23: 38720.759 | AM23: 39410.766 | AN23: 40128.372 | AO23: 40874.683 | AP23: 41650.846 | AQ23: 42458.056 | AR23: 43297.554 | AS23: 44170.632 | AT23: 45078.633 | AU23: 46022.955 | AV23: 47005.049 | AW23: 48026.427 | AX23: 49088.66 | AY23: 50099.189 | AZ23: 50960.872 | BA23: 51857.023 | BB23: 52789.02
A24: Total Net Income | V24: =if(OR(V22>0,V23>0),sum(V22:V23),) | W24: =if(OR(W22>0,W23>0),sum(W22:W23),) -> 108009.35 | X24: =if(OR(X22>0,X23>0),sum(X22:X23),) -> 109861.07 | Y24: =if(OR(Y22>0,Y23>0),sum(Y22:Y23),) -> 111759.08 | Z24: =if(OR(Z22>0,Z23>0),sum(Z22:Z23),) -> 113704.55 | AA24: =if(OR(AA22>0,AA23>0),sum(AA22:AA23),) -> 118245.15 | AB24: =if(OR(AB22>0,AB23>0),sum(AB22:AB23),) -> 120289.1 | AC24: =if(OR(AC22>0,AC23>0),sum(AC22:AC23),) -> 122384.15 | ... BT24: =if(OR(BT22>0,BT23>0),sum(BT22:BT23),)

Sheet Settings
A1: License Key | B1: 1JHE-0U5P-NYPC-JA12
A30: Age | B30: Net NPV | C30: Total Pension | D30: Net Income Total | E30: Tax Total
A31: 55 | B31: 0 | C31: 0 | D31: 0 | E31: 0
A32: 56 | B32: 0 | C32: 0 | D32: 0 | E32: 0
A33: 57 | B33: 0 | C33: 0 | D33: 0 | E33: 0
A34: 58 | B34: 108009.35 | C34: 127593.77 | D34: 108009.35 | E34: 19584.422
A35: 59 | B35: 107547.79 | C35: 130310.52 | D35: 109861.07 | E35: 20449.445
A36: 60 | B36: 107097.48 | C36: 133095.18 | D36: 111759.08 | E36: 21336.093
A37: 61 | B37: 106658.16 | C37: 135949.45 | D37: 113704.55 | E37: 22244.907
A38: 62 | B38: 108947.4 | C38: 141875.09 | D38: 118245.15 | E38: 23629.94
A39: 63 | B39: 108462.96 | C39: 144873.86 | D39: 120289.1 | E39: 24584.763
A40: 64 | B40: 107990.34 | C40: 147947.61 | D40: 122384.15 | E40: 25563.457
A41: 65 | B41: 107529.24 | C41: 151098.19 | D41: 124531.58 | E41: 26566.618
A42: 66 | B42: 107079.38 | C42: 154327.55 | D42: 126732.69 | E42: 27594.858
... A65: 89 | B65: 82432.747 | C65: 202494.95 | D65: 152629.99 | E65: 49864.956
